[{"title":"200Pcs Plastic S Clips For Loom Rubber Band Refills Bracelet Bands C ZQ","price":"RMB 22.53","url":"https://i.ebayimg.com/thumbs/images/g/RroAAOSwUAxbUZip/s-l800.webp","shipping":"+RMB 20.32 shipping","source_url":"https://www.ebay.com/itm/193242744769?hash=item2cfe2a47c1:g:RroAAOSwUAxbUZip"},{"title":"Silver Gypsophila Flash Chain Anklets Bracelet Women Barefoot Jewellery Gift","price":"RMB 12.07","url":"https://i.ebayimg.com/thumbs/images/g/lUwAAOSwCgBgnUhU/s-l800.webp","shipping":"Free International Shipping","source_url":"https://www.ebay.com/itm/203977291966?hash=item2f7dfe78be:g:lUwAAOSwCgBgnUhU"},{"title":"18K Yellow Gold Filled Women Classic Clear Topaz Hoop Huggie Earrings Jewelry","price":"RMB 15.31","url":"https://i.ebayimg.com/thumbs/images/g/FEkAAOSw0lxgIEba/s-l800.webp","shipping":"+RMB 33.35 shipping","source_url":"https://www.ebay.com/itm/224343677492?hash=item343becda34:g:FEkAAOSw0lxgIEba"},{"title":"18K Yellow Gold Filled Clear Double Row Topaz Women Huggie Earrings Jewelry","price":"RMB 15.31","url":"https://i.ebayimg.com/thumbs/images/g/-wMAAOSwbMtcV1fI/s-l800.webp","shipping":"+RMB 33.35 shipping","source_url":"https://www.ebay.com/itm/223364842538?hash=item340195042a:g:-wMAAOSwbMtcV1fI"},{"title":"Car Spare Wheel Tire Covers For Hummer H2 Silver Logo Heavy Duty Vinyl 34\" 35\"","price":"RMB 259.88","url":"https://i.ebayimg.com/thumbs/images/g/-pQAAOSwy~hhsh-y/s-l800.webp","shipping":"Free International Shipping","source_url":"https://www.ebay.com/itm/363650634929?hash=item54ab4454b1:g:-pQAAOSwy~hhsh-y"},{"title":"Car Spare Wheel Tire Covers For Hummer H3 Logo Heavy Duty Leather Vinyl 32\" 33\"","price":"RMB 239.83","url":"https://i.ebayimg.com/thumbs/images/g/iGkAAOSwDNFhsh6R/s-l800.webp","shipping":"Free International Shipping","source_url":"https://www.ebay.com/itm/363650632682?hash=item54ab444bea:g:iGkAAOSwDNFhsh6R"},{"title":"Car Spare Wheel Tire Covers For Hummer H3 Logo Heavy Duty Leather Vinyl 30\" 31\"","price":"RMB 239.83","url":"https://i.ebayimg.com/thumbs/images/g/iGkAAOSwDNFhsh6R/s-l800.webp","shipping":"Free International Shipping","source_url":"https://www.ebay.com/itm/363650632051?hash=item54ab444973:g:iGkAAOSwDNFhsh6R"},{"title":"Unisex Solid Stretch Headband Sports Yoga Gym Hair Band Wrap Sweatband Headwrap","price":"RMB 6.62","url":"https://i.ebayimg.com/thumbs/images/g/QigAAOSwAiFhlh7T/s-l800.webp","shipping":"Free International Shipping","source_url":"https://www.ebay.com/itm/384607623896?hash=item598c669ad8:g:QigAAOSwAiFhlh7T"},{"title":"Car Spare Wheel Tire Covers For Hummer H3 Silver Logo Heavy Duty Vinyl 32\" 33\"","price":"RMB 239.83","url":"https://i.ebayimg.com/thumbs/images/g/sXoAAOSwy6dhsh-I/s-l800.webp","shipping":"Free International Shipping","source_url":"https://www.ebay.com/itm/363765227203?hash=item54b218dec3:g:sXoAAOSwy6dhsh-I"},{"title":"Neutral Switch Assembly Fits For Yamaha Rhino 660 YXR660F 04-07 5KM-82540-01-00","price":"RMB 160.42","url":"https://i.ebayimg.com/thumbs/images/g/j7QAAOSwNKhimLIH/s-l800.webp","shipping":"Free International Shipping","source_url":"https://www.ebay.com/itm/275335355390?hash=item401b441bfe:g:j7QAAOSwNKhimLIH"},{"title":"Square 40-130mm 120PC Mix Cassette Tape Machine Belt Assorted Common Rubber Belt","price":"RMB 32.96","url":"https://i.ebayimg.com/thumbs/images/g/f2sAAOSwsWBhiya8/s-l800.webp","shipping":"+RMB 18.99 shipping","source_url":"https://www.ebay.com/itm/304219500331?hash=item46d4e52f2b:g:f2sAAOSwsWBhiya8"},{"title":"3Ports Expander Charger USB 3.0 Hub Splitter Adapter Laptop NEW For PC Q .DECO","price":"RMB 11.53 to RMB 13.86","url":"https://i.ebayimg.com/thumbs/images/g/tMYAAOSwAyViWRa-/s-l800.webp","shipping":"Free International Shipping","source_url":"https://www.ebay.com/itm/295018688517?hash=item44b07bf005:g:tMYAAOSwAyViWRa-"},{"title":"Womens Summer Halter Tie Back Solid Color Pockets Sleeveless Wide Leg Jumpsuit","price":"RMB 185.42","url":"https://i.ebayimg.com/thumbs/images/g/LZ8AAOSwbwRiYQc0/s-l800.webp","shipping":"Free International Shipping","source_url":"https://www.ebay.com/itm/115353375666?hash=item1adb98d3b2:g:LZ8AAOSwbwRiYQc0"},{"title":"Arthritis Pain Relief Ginger Heating Sticker Joint Ache Patch Knee Plaster New","price":"RMB 27.41","url":"https://i.ebayimg.com/thumbs/images/g/zNwAAOSwybRilLRU/s-l800.webp","shipping":"Free International Shipping","source_url":"https://www.ebay.com/itm/195095030140?hash=item2d6c91e97c:g:zNwAAOSwybRilLRU"},{"title":"Leopard 58113 700KV 8000W Brushless Motor for 1/5 Car - DHL Express to US!","price":"RMB 1,269.34","url":"https://i.ebayimg.com/thumbs/images/g/WlYAAOSwjF5hIycG/s-l800.webp","shipping":"+RMB 113.63 shipping","source_url":"https://www.ebay.com/itm/265160326291?hash=item3dbcc97c93:g:WlYAAOSwjF5hIycG"},{"title":"INBIKE 5mm Gel Padded Touch Screen Full Finger Cycling Gloves Woman Men Fall USE","price":"RMB 213.83","url":"https://i.ebayimg.com/thumbs/images/g/LpIAAOSw1CBZ3xCI/s-l800.webp","shipping":"Free International Shipping","source_url":"https://www.ebay.com/itm/192331773348?hash=item2cc7ddf5a4:g:LpIAAOSw1CBZ3xCI"},{"title":"40-130mm 50PCS Mix Square Cassette Tape Machine Belt Assorted Common Rubber Belt","price":"RMB 53.41","url":"https://i.ebayimg.com/thumbs/images/g/IcUAAOSwuJtc6Rb0/s-l800.webp","shipping":"Free International Shipping","source_url":"https://www.ebay.com/itm/223143540337?hash=item33f4643671:g:IcUAAOSwuJtc6Rb0"},{"title":"NWT YINGFA 9201 MEN'S COMPETITION TRAINING RACING SWIMMING TRUNKS BRIEF ALL SIZE","price":"RMB 134.04","url":"https://i.ebayimg.com/thumbs/images/g/RAQAAOSwWZVazBMd/s-l800.webp","shipping":"Free International Shipping","source_url":"https://www.ebay.com/itm/222917720753?hash=item33e6ee7ab1:g:RAQAAOSwWZVazBMd"},{"title":"40x Undertray Clips Screws Engine Under Cover Splash Guard Shield For BMW","price":"RMB 79.34","url":"https://i.ebayimg.com/thumbs/images/g/DRUAAOSw6iRhQCZ~/s-l800.webp","shipping":"Free International Shipping","source_url":"https://www.ebay.com/itm/284451792216?hash=item423aa5e558:g:DRUAAOSw6iRhQCZ~"},{"title":"Black Titanium Interior Door Anti-Kick Panel Trim 4PCS For Ford Ranger 2015-2022","price":"RMB 1,080.18","url":"https://i.ebayimg.com/thumbs/images/g/ntMAAOSwvQNik7zR/s-l800.webp","shipping":"+RMB 334.21 shipping","source_url":"https://www.ebay.com/itm/195093492396?hash=item2d6c7a72ac:g:ntMAAOSwvQNik7zR"},{"title":"unique Coleoptera beetle Burmite Myanmar Burma Amber insect fossil dinosaur age","price":"RMB 10.09","url":"https://i.ebayimg.com/thumbs/images/g/DmMAAOSw6XdimgkV/s-l800.webp","shipping":"Free International Shipping","source_url":"https://www.ebay.com/itm/265720866028?hash=item3dde32a4ec:g:DmMAAOSw6XdimgkV"},{"title":"Silver Synthetic White Simulated Opal Engagement Women's Studs Dang Jewelry Gift","price":"RMB 14.55","url":"https://i.ebayimg.com/thumbs/images/g/MwEAAOSwAGlij1Fx/s-l800.webp","shipping":"Free International Shipping","source_url":"https://www.ebay.com/itm/275339277781?hash=item401b7ff5d5:g:MwEAAOSwAGlij1Fx"},{"title":"990-9413.1B car computer chip board","price":"RMB 134.12","url":"https://i.ebayimg.com/thumbs/images/g/kowAAOSwXedetlTj/s-l800.webp","shipping":"+RMB 50.21 shipping","source_url":"https://www.ebay.com/itm/233582831347?hash=item36629f26f3:g:kowAAOSwXedetlTj"},{"title":"Long Cotton Traditional Chinese Clothes Men Tang Suit Top Kung Fu Blouse Shirt","price":"RMB 120.58","url":"https://i.ebayimg.com/thumbs/images/g/xW8AAOSwPKNgUt~f/s-l800.webp","shipping":"+RMB 39.97 shipping","source_url":"https://www.ebay.com/itm/264782743439?hash=item3da648078f:g:xW8AAOSwPKNgUt~f"},{"title":"4PCS For Ford Door Protector Door Side Edge Protection Guards Stickers Decals","price":"RMB 86.83","url":"https://i.ebayimg.com/thumbs/images/g/X-IAAOSwCXdgdbS7/s-l800.webp","shipping":"Free International Shipping","source_url":"https://www.ebay.com/itm/224575279375?hash=item3449bad10f:g:X-IAAOSwCXdgdbS7"},{"title":"360° Full Protect Metal Magnetic Double Sided Glass Case Cover For SmartPhones","price":"RMB 60.09 to RMB 73.46","url":"https://i.ebayimg.com/thumbs/images/g/MZYAAOSwTBRdSpdZ/s-l800.webp","shipping":"+RMB 19.99 shipping","source_url":"https://www.ebay.com/itm/183912375951?hash=item2ad208268f:g:MZYAAOSwTBRdSpdZ"},{"title":"Sunroof Window Switch Button Cover For Mercedes W204 W212 W218 C E CLS Class","price":"RMB 126.93","url":"https://i.ebayimg.com/thumbs/images/g/dX4AAOSwzxpiOUst/s-l800.webp","shipping":"Free International Shipping","source_url":"https://www.ebay.com/itm/275225697095?hash=item4014badb47:g:dX4AAOSwzxpiOUst"},{"title":"Women Silver Cat Animal Crystal Pearl Asymmetric Stud Earrings Jewelry Fashion","price":"RMB 5.24 to RMB 15.45","url":"https://i.ebayimg.com/thumbs/images/g/DZgAAOSw~9tifcsw/s-l800.webp","shipping":"Free International Shipping","source_url":"https://www.ebay.com/itm/373583911415?hash=item56fb5619f7:g:DZgAAOSw~9tifcsw"},{"title":"Men's Sexy Shiny Metallic Wetlook Drawstring Boxer Shorts Swim Trunks Underwear","price":"RMB 41.49","url":"https://i.ebayimg.com/thumbs/images/g/EPkAAOSwsFpaHK~-/s-l800.webp","shipping":"Free International Shipping","source_url":"https://www.ebay.com/itm/302996235603?hash=item468bfba553:g:EPkAAOSwsFpaHK~-"},{"title":"10 PCS New LR44 AG13 L1154 1.5V Alkaline Button Cell Coin Pack Battery Batteries","price":"RMB 16.83","url":"https://i.ebayimg.com/thumbs/images/g/DAkAAOSwZQRYWNl8/s-l800.webp","shipping":"Free International Shipping","source_url":"https://www.ebay.com/itm/333544232075?hash=item4da8c9148b:g:DAkAAOSwZQRYWNl8"},{"title":"5pcs Ceramic Replacement Cutter Fits Most Andis Oster Wahl AG/A5 Clipper Blades","price":"RMB 106.21","url":"https://i.ebayimg.com/thumbs/images/g/5yMAAOSwquxgUCFz/s-l800.webp","shipping":"Free International Shipping","source_url":"https://www.ebay.com/itm/333922850705?hash=item4dbf5a5791:g:5yMAAOSwquxgUCFz"},{"title":"5pcs natural blue gold sand hand carved crystal mushroom reiki healing gems","price":"RMB 15.04","url":"https://i.ebayimg.com/thumbs/images/g/epkAAOSwDFtimgi2/s-l800.webp","shipping":"Free International Shipping","source_url":"https://www.ebay.com/itm/314022408530?hash=item491d31b152:g:epkAAOSwDFtimgi2"},{"title":"50Pcs Car Bumper Door Trim 8mm Hole Plastic Push Pin Rivet Clamp Fastener Clip","price":"RMB 57.75","url":"https://i.ebayimg.com/thumbs/images/g/eTIAAOSw2qFinmVL/s-l800.webp","shipping":"Free International Shipping","source_url":"https://www.ebay.com/itm/363865080353?hash=item54b80c8221:g:eTIAAOSw2qFinmVL"},{"title":"Natural Bear Gummies for Stress Relief -Great for Pain,Sleep Insomnia & Anxiety","price":"RMB 73.46 to RMB 173.72","url":"https://i.ebayimg.com/thumbs/images/g/GrIAAOSwnBJiJi4l/s-l800.webp","shipping":"Free International Shipping","source_url":"https://www.ebay.com/itm/255422820893?hash=item3b7862f21d:g:GrIAAOSwnBJiJi4l"},{"title":"Womens Gold Double O-Ring Buckle Genuine Leather Belt For Jeans Pants Plus Size","price":"RMB 60.09 to RMB 140.30","url":"https://i.ebayimg.com/thumbs/images/g/Pu8AAOSwRAphbO1D/s-l800.webp","shipping":"Free International Shipping","source_url":"https://www.ebay.com/itm/403215103172?hash=item5de17e34c4:g:Pu8AAOSwRAphbO1D"},{"title":"3L/Min Portable 32W 𝓞2 Concentrator Machine Efficient 28+2% Air Purifier 110V","price":"RMB 1,763.91","url":"https://i.ebayimg.com/thumbs/images/g/cKMAAOSwDgBiR7iy/s-l800.webp","shipping":"Free International Shipping","source_url":"https://www.ebay.com/itm/294898978328?hash=item44a9594e18:g:cKMAAOSwDgBiR7iy"},{"title":"121mm Aluminium Cigarette case box Holder carrier Seal Dampproof Waterproof","price":"RMB 123.66","url":"https://i.ebayimg.com/thumbs/images/g/Q20AAOSwSw1cvTRt/s-l800.webp","shipping":"+RMB 53.41 shipping","source_url":"https://www.ebay.com/itm/314007604963?hash=item491c4fcee3:g:Q20AAOSwSw1cvTRt"},{"title":"55g Natural Polished Pork Stone Meat Rough Specimen","price":"RMB 31.08","url":"https://i.ebayimg.com/thumbs/images/g/R1AAAOSwZ8himgiJ/s-l800.webp","shipping":"Free International Shipping","source_url":"https://www.ebay.com/itm/314022408276?hash=item491d31b054:g:R1AAAOSwZ8himgiJ"},{"title":"Fashion Gorgeous 925 Silver Drop Earrings for Women Crystal Jewelry A Pair/set","price":"RMB 19.20 to RMB 22.47","url":"https://i.ebayimg.com/thumbs/images/g/sY8AAOSw~Ihh53HZ/s-l800.webp","shipping":"+RMB 16.68 shipping","source_url":"https://www.ebay.com/itm/384446148521?hash=item5982c6afa9:g:sY8AAOSw~Ihh53HZ"},{"title":"For ADDA FAN DC BRUSHLESS Model AD1212HB-A71GL 12V 0.37A 2 PIN POWER #9","price":"RMB 85.49","url":"https://i.ebayimg.com/thumbs/images/g/sXkAAOSwOq9gucnv/s-l800.webp","shipping":"Free International Shipping","source_url":"https://www.ebay.com/itm/164897635309?hash=item2664aa3bed:g:sXkAAOSwOq9gucnv"},{"title":"Red For Honda Civic B Series Type R DC2 EK4 EK9 B16A Silicone Radiator Hose Kit","price":"RMB 501.25","url":"https://i.ebayimg.com/thumbs/images/g/-XQAAOSwdnhes6Ow/s-l800.webp","shipping":"Free International Shipping","source_url":"https://www.ebay.com/itm/174760279036?hash=item28b0863bfc:g:-XQAAOSwdnhes6Ow"},{"title":"Women V Neck Lace Crochet Button Down Blouse Eyelet Hollow Out Short Sleeve Tops","price":"RMB 133.62 to RMB 153.67","url":"https://i.ebayimg.com/thumbs/images/g/7dkAAOSwMA5gmj54/s-l800.webp","shipping":"Free International Shipping","source_url":"https://www.ebay.com/itm/265156344452?hash=item3dbc8cba84:g:7dkAAOSwMA5gmj54"},{"title":"Bumper Reflector Left Right For Acura TSX Sedan 2009 10 11-2014 Rear Side Light","price":"RMB 131.41","url":"https://i.ebayimg.com/thumbs/images/g/PoMAAOSwCdRe1zp8/s-l800.webp","shipping":"Free International Shipping","source_url":"https://www.ebay.com/itm/164230234566?hash=item263ce281c6:g:PoMAAOSwCdRe1zp8"},{"title":"46 Pcs Lot Cute DIY Paper Stickers Kawaii Stationery Scrapbooking Diary Sticker","price":"RMB 12.63","url":"https://i.ebayimg.com/thumbs/images/g/6fQAAOSwrnNfUwEm/s-l800.webp","shipping":"+RMB 31.35 shipping","source_url":"https://www.ebay.com/itm/293938599598?hash=item44701b16ae:g:6fQAAOSwrnNfUwEm"},{"title":"For Mercedes-Benz-GL-GLA-GLB-GLC-GLS-GLK-2007-2022 Car trunk mat","price":"RMB 307.41","url":"https://i.ebayimg.com/thumbs/images/g/~3YAAOSwuudiM0TQ/s-l800.webp","shipping":"+RMB 26.67 shipping","source_url":"https://www.ebay.com/itm/363818283250?hash=item54b54270f2:g:~3YAAOSwuudiM0TQ"},{"title":"Sound-Activated LED Light Up Glass Phone Case Cover for iPhone 13 11 12 Pro Max","price":"RMB 93.51","url":"https://i.ebayimg.com/thumbs/images/g/S0kAAOSwIsRhX~6z/s-l800.webp","shipping":"Free International Shipping","source_url":"https://www.ebay.com/itm/393618595459?hash=item5ba57f1e83:g:S0kAAOSwIsRhX~6z"},{"title":"Sound-Activated LED Light-up Smile Glass Phone Case Cover for iPhone 7~13 ProMax","price":"RMB 102.20 to RMB 108.22","url":"https://i.ebayimg.com/thumbs/images/g/Fm0AAOSwqV1fMM7K/s-l800.webp","shipping":"Free International Shipping","source_url":"https://www.ebay.com/itm/154040355669?hash=item23dd854b55:g:Fm0AAOSwqV1fMM7K"},{"title":"Induction Anime LED Light-up Glass Phone Case Cover for iPhone 12 Pro 13 Pro Max","price":"RMB 102.20 to RMB 108.22","url":"https://i.ebayimg.com/thumbs/images/g/m0sAAOSwPitfuIod/s-l800.webp","shipping":"Free International Shipping","source_url":"https://www.ebay.com/itm/154353623924?hash=item23f0316374:g:m0sAAOSwPitfuIod"},{"title":"4x Fuel Injectors Nozzle Genuine Bosch For VW Golf R MK7 Audi S3 8V TTS 2.0 TFSI","price":"RMB 1,537.38","url":"https://i.ebayimg.com/thumbs/images/g/B0MAAOSwjqVZJVMG/s-l800.webp","shipping":"Free International Shipping","source_url":"https://www.ebay.com/itm/233325010854?epid=8027479637&hash=item3653411fa6:g:B0MAAOSwjqVZJVMG"},{"title":"Case for Google Pixel 6 Pro XL Luxury Textile leather Skin Phone Case Cover","price":"RMB 26.40","url":"https://i.ebayimg.com/thumbs/images/g/YKAAAOSweEJg7qCo/s-l800.webp","shipping":"Free International Shipping","source_url":"https://www.ebay.com/itm/304256584893?hash=item46d71b0cbd:g:YKAAAOSweEJg7qCo"},{"title":"Chrome Car Front Fog Light Lamp Cover Trim For 2018-2020 Subaru Crosstrek XV","price":"RMB 122.32","url":"https://i.ebayimg.com/thumbs/images/g/pAoAAOSws1liCwDz/s-l800.webp","shipping":"Free International Shipping","source_url":"https://www.ebay.com/itm/194834167577?hash=item2d5d057719:g:pAoAAOSws1liCwDz"},{"title":"For Google Pixel 6 Pro 5 5a 4a 4 XL Shockproof Fiber Carbon Silicone Case Cover","price":"RMB 23.80 to RMB 27.81","url":"https://i.ebayimg.com/thumbs/images/g/togAAOSwBpBiVReD/s-l800.webp","shipping":"+RMB 19.99 shipping","source_url":"https://www.ebay.com/itm/134083488345?hash=item1f37ffaa59:g:togAAOSwBpBiVReD"},{"title":"Original Flashlight Flex Cable Replacement for OnePlus 7 Pro","price":"RMB 53.94","url":"https://i.ebayimg.com/thumbs/images/g/o-gAAOSwrpReGLsH/s-l800.webp","shipping":"Free International Shipping","source_url":"https://www.ebay.com/itm/333474836871?hash=item4da4a63187:g:o-gAAOSwrpReGLsH"},{"title":"Vintage 925 Silver White Sapphire Handmade Drop Dangle Earrings Hook Girl Gift","price":"RMB 2.91","url":"https://i.ebayimg.com/thumbs/images/g/KVIAAOSwxcVinKun/s-l800.webp","shipping":"Free International Shipping","source_url":"https://www.ebay.com/itm/384932349755?hash=item599fc1873b:g:KVIAAOSwxcVinKun"},{"title":"CGA EGA RGB to VGA GAME Video Converter pcb VGA Output Game Convert GBS8200","price":"RMB 160.42","url":"https://i.ebayimg.com/thumbs/images/g/cD4AAOSwt2FcpCCK/s-l800.webp","shipping":"+RMB 26.74 shipping","source_url":"https://www.ebay.com/itm/313519427480?hash=item48ff36cf98:g:cD4AAOSwt2FcpCCK"},{"title":"2Pcs Car Rear Trunk Emblems Decal Accessories FUCK-IT Edition Badge Side Sticker","price":"RMB 56.75","url":"https://i.ebayimg.com/thumbs/images/g/IksAAOSw3iRingrd/s-l800.webp","shipping":"Free International Shipping","source_url":"https://www.ebay.com/itm/134140149974?hash=item1f3b6040d6:g:IksAAOSw3iRingrd"},{"title":"New Classic Checks Dark Blue Blue JACQUARD WOVEN 100% Silk Men's Tie Necktie","price":"RMB 53.41","url":"https://i.ebayimg.com/thumbs/images/g/6kYAAOSwHmhe3lXb/s-l800.webp","shipping":"Free International Shipping","source_url":"https://www.ebay.com/itm/293606823464?hash=item445c549628:g:6kYAAOSwHmhe3lXb"},{"title":"New Classic Checks Blue Black JACQUARD WOVEN Silk Men's Tie Necktie","price":"RMB 60.09","url":"https://i.ebayimg.com/thumbs/images/g/70wAAOSwwmlcqMJY/s-l800.webp","shipping":"Free International Shipping","source_url":"https://www.ebay.com/itm/254473700571?hash=item3b3fd084db:g:70wAAOSwwmlcqMJY"},{"title":"New Classic Checks Purple Gray Black JACQUARD WOVEN 100% Silk Men's Tie Necktie","price":"RMB 60.09","url":"https://i.ebayimg.com/thumbs/images/g/II0AAOSwubRXHlO6/s-l800.webp","shipping":"Free International Shipping","source_url":"https://www.ebay.com/itm/262816409310?hash=item3d311426de:g:II0AAOSwubRXHlO6"},{"title":"New Classic Checks Blue White JACQUARD WOVEN 100% Silk Men's Tie Necktie","price":"RMB 46.72","url":"https://i.ebayimg.com/thumbs/images/g/MjMAAOSwnipWT-rN/s-l800.webp","shipping":"Free International Shipping","source_url":"https://www.ebay.com/itm/264177503153?hash=item3d8234cbb1:g:MjMAAOSwnipWT-rN"},{"title":"New Classic Checks Red White Black JACQUARD WOVEN 100% Silk Men's Tie Necktie","price":"RMB 60.09","url":"https://i.ebayimg.com/thumbs/images/g/KgUAAOSw9mFbAix3/s-l800.webp","shipping":"Free International Shipping","source_url":"https://www.ebay.com/itm/264733349577?hash=item3da35656c9:g:KgUAAOSw9mFbAix3"},{"title":"For Dodge Car Floor Mats Carpets Custom Auto FloorMats Car Floor Protector Rug","price":"RMB 634.74","url":"https://i.ebayimg.com/thumbs/images/g/YZUAAOSwPeRdtIwS/s-l800.webp","shipping":"Free International Shipping","source_url":"https://www.ebay.com/itm/224952133248?hash=item3460312680:g:YZUAAOSwPeRdtIwS"},{"title":"Head Rope Camellia Rhinestone Crystal Hair Ring Tie Geometric Flower Accessories","price":"RMB 97.26","url":"https://i.ebayimg.com/thumbs/images/g/K-IAAOSwPIlhFLtE/s-l800.webp","shipping":"Free International Shipping","source_url":"https://www.ebay.com/itm/393563918200?hash=item5ba23ccf78:g:K-IAAOSwPIlhFLtE"},{"title":"2PC 1800mAh NTN8293 NTN8294 RNN4006 Battery for MOTOROLA XTS3000 XTS3500 XTS5000","price":"RMB 367.57","url":"https://i.ebayimg.com/thumbs/images/g/eO8AAOSwuyNhFhoW/s-l800.webp","shipping":"Free International Shipping","source_url":"https://www.ebay.com/itm/154082688493?hash=item23e00b3ded:g:eO8AAOSwuyNhFhoW"},{"title":"Industrial Filter Sock Bags 1-200um Micron Mesh PP/PE 4\"x9\" 4\"x15\" 6\"x20\"New","price":"RMB 57.42 to RMB 71.67","url":"https://i.ebayimg.com/thumbs/images/g/NpUAAOSwzrxUtKOW/s-l800.webp","shipping":"+RMB 40.24 shipping","source_url":"https://www.ebay.com/itm/281881619314?hash=item41a1742b72:g:NpUAAOSwzrxUtKOW"},{"title":"10pcs CSD19536KTT TO-263","price":"RMB 90.24","url":"https://i.ebayimg.com/thumbs/images/g/V5wAAOSwWrxcOgdf/s-l800.webp","shipping":"+RMB 16.58 shipping","source_url":"https://www.ebay.com/itm/302891890269?hash=item4685c3765d:g:V5wAAOSwWrxcOgdf"},{"title":"10PCS IPB020N08N5 020N08N5 TO-263","price":"RMB 70.18","url":"https://i.ebayimg.com/thumbs/images/g/Z7gAAOSwuFxg3e5J/s-l800.webp","shipping":"+RMB 16.58 shipping","source_url":"https://www.ebay.com/itm/303141396430?hash=item4694a29fce:g:Z7gAAOSwuFxg3e5J"},{"title":"12x Car Interior Door Lock Screw Protector Cover Anti-Rust Cap Trim Accessories","price":"RMB 52.67","url":"https://i.ebayimg.com/thumbs/images/g/P8gAAOSw1JViTo4U/s-l800.webp","shipping":"Free International Shipping","source_url":"https://www.ebay.com/itm/334394956468?hash=item4ddb7e1ab4:g:P8gAAOSw1JViTo4U"},{"title":"US USA Flag Stickers American Car Logo Emblem Metal Badge Decal Auto Accessories","price":"RMB 19.10","url":"https://i.ebayimg.com/thumbs/images/g/pQgAAOSwwBdhxDTY/s-l800.webp","shipping":"Free International Shipping","source_url":"https://www.ebay.com/itm/154762987599?hash=item240897c84f:g:pQgAAOSwwBdhxDTY"},{"title":"Certificate 18mm Natural Mexico Sky Blue Amber Beads Bracelet 7.5”","price":"RMB 31.82","url":"https://i.ebayimg.com/thumbs/images/g/r6wAAOSwlXliYCOb/s-l800.webp","shipping":"Free International Shipping","source_url":"https://www.ebay.com/itm/374115115729?hash=item571affa2d1:g:r6wAAOSwlXliYCOb"},{"title":"NEW LISTINGMens U-Convex Underwear Pouch Breathable Sports Boxer Briefs Shorts Bulge Pouch","price":"RMB 59.68 to RMB 66.40","url":"https://i.ebayimg.com/thumbs/images/g/GKMAAOSwyvViom18/s-l800.webp","shipping":"+RMB 18.15 shipping","source_url":"https://www.ebay.com/itm/203987065742?hash=item2f7e939b8e:g:GKMAAOSwyvViom18"},{"title":"Kpop Stray Kids T-SHIRT MANIAC Concert Tshirt Unisex Cotton TEE","price":"RMB 102.27","url":"https://i.ebayimg.com/thumbs/images/g/o0IAAOSwbuZig45S/s-l800.webp","shipping":"Free International Shipping","source_url":"https://www.ebay.com/itm/125320428741?hash=item1d2dadfcc5:g:o0IAAOSwbuZig45S"},{"title":"Carbon Fiber Style for BMW F10 Sedan M5 Side Fender Cover Grille 11-17 4DR ABS","price":"RMB 325.59","url":"https://i.ebayimg.com/thumbs/images/g/7Z4AAOSwQ3le5O-S/s-l800.webp","shipping":"Free International Shipping","source_url":"https://www.ebay.com/itm/303595315731?hash=item46afb0e213:g:7Z4AAOSwQ3le5O-S"},{"title":"Dog Collar & Leash Set Soft Padded Braided Leather Personalized Free Engrave","price":"RMB 56.75 to RMB 123.59","url":"https://i.ebayimg.com/thumbs/images/g/N0IAAOSwHixZl5DL/s-l800.webp","shipping":"Free International Shipping","source_url":"https://www.ebay.com/itm/162637061648?hash=item25ddec9e10:g:N0IAAOSwHixZl5DL"},{"title":"9V-Battery Box Case Holder Replacement For EQ 7545R Acoustic Guitar Pickup Parts","price":"RMB 42.38","url":"https://i.ebayimg.com/thumbs/images/g/Nv4AAOSwbGthyrKM/s-l800.webp","shipping":"Free International Shipping","source_url":"https://www.ebay.com/itm/373843795311?hash=item570ad39d6f:g:Nv4AAOSwbGthyrKM"},{"title":"Diamond Core Bit Hole Saw Drill Bit For Marble Granite Brick Ceramic Concrete","price":"RMB 33.42 to RMB 207.21","url":"https://i.ebayimg.com/thumbs/images/g/FVEAAOSwAQVhgi4~/s-l800.webp","shipping":"Free International Shipping","source_url":"https://www.ebay.com/itm/224673591466?hash=item344f96f0aa:g:FVEAAOSwAQVhgi4~"},{"title":"Honda Civic Driver Side Steering Wheel Air SRS 2016 2017 2018 2019 2020 Bag","price":"RMB 661.74","url":"https://i.ebayimg.com/thumbs/images/g/e2oAAOSwK7BilwpD/s-l800.webp","shipping":"+RMB 1,002.64 shipping","source_url":"https://www.ebay.com/itm/295022279015?hash=item44b0b2b967:g:e2oAAOSwK7BilwpD"},{"title":"Red Wine Bottle Opener Cork Remover Easy Air Pump Pressure Tool New","price":"RMB 22.39","url":"https://i.ebayimg.com/thumbs/images/g/R4MAAOSw8lhbyoTs/s-l800.webp","shipping":"+RMB 27.74 shipping","source_url":"https://www.ebay.com/itm/362781691822?hash=item5477794fae:g:R4MAAOSw8lhbyoTs"},{"title":"NO Backlit Keyboard For Gateway GWTN141-1PR GWTN141-1 1BK 1BL GWTN141-5 English","price":"RMB 167.11","url":"https://i.ebayimg.com/thumbs/images/g/pmMAAOSwF~JiMtxX/s-l800.webp","shipping":"+RMB 120.32 shipping","source_url":"https://www.ebay.com/itm/284707666504?hash=item4249e63a48:g:pmMAAOSwF~JiMtxX"},{"title":"Carbon fiber Navigation Adjustment button panel Cover Trim For FORD Maverick","price":"RMB 233.95","url":"https://i.ebayimg.com/thumbs/images/g/2JgAAOSwIn1iceoz/s-l800.webp","shipping":"Free International Shipping","source_url":"https://www.ebay.com/itm/195025732072?hash=item2d687081e8:g:2JgAAOSwIn1iceoz"},{"title":"Carbon Fiber Central Control Gear Shift Panel trim For FORD Maverick 2022+","price":"RMB 333.55","url":"https://i.ebayimg.com/thumbs/images/g/mW8AAOSwCg1iceo0/s-l800.webp","shipping":"Free International Shipping","source_url":"https://www.ebay.com/itm/195025732148?hash=item2d68708234:g:mW8AAOSwCg1iceo0"},{"title":"Carbon Fiber Interior Dashboard Frame Trim Cover Fit For FORD Maverick 2022+","price":"RMB 266.70","url":"https://i.ebayimg.com/thumbs/images/g/TkMAAOSwE0lifLL6/s-l800.webp","shipping":"Free International Shipping","source_url":"https://www.ebay.com/itm/195047315260?hash=item2d69b9d73c:g:TkMAAOSwE0lifLL6"},{"title":"Carbon fiber Interior Steering Wheel Trim Cover Fit For FORD Maverick 2022+","price":"RMB 267.30","url":"https://i.ebayimg.com/thumbs/images/g/D6QAAOSwP7Ziceox/s-l800.webp","shipping":"Free International Shipping","source_url":"https://www.ebay.com/itm/203934817509?hash=item2f7b765ce5:g:D6QAAOSwP7Ziceox"},{"title":"Carbon fiber interior Central Control A/C Panel Cover Trim For FORD Maverick","price":"RMB 266.70","url":"https://i.ebayimg.com/thumbs/images/g/GagAAOSwm4Viceoz/s-l800.webp","shipping":"Free International Shipping","source_url":"https://www.ebay.com/itm/203934817799?hash=item2f7b765e07:g:GagAAOSwm4Viceoz"},{"title":"25mmx25mm Plastic Square Table Chair Leg Feet Tube Pipe Insert End Cap 20 PCS","price":"RMB 65.10","url":"https://i.ebayimg.com/thumbs/images/g/gncAAOSwI-RiPyM4/s-l800.webp","shipping":"Free International Shipping","source_url":"https://www.ebay.com/itm/393905226070?epid=12006312574&hash=item5bb694c156:g:gncAAOSwI-RiPyM4"},{"title":"2x Chrome Black 5.7L Emblem 5.7 Logo Car Side Badge Metal Sticker Sport Turbo","price":"RMB 73.46","url":"https://i.ebayimg.com/thumbs/images/g/iMIAAOSwM6th6iuJ/s-l800.webp","shipping":"Free International Shipping","source_url":"https://www.ebay.com/itm/175120586776?hash=item28c6001818:g:iMIAAOSwM6th6iuJ"},{"title":"Home Combustible Gas Leak Detector Propane Butane LPG Natural Gas Sensor Durable","price":"RMB 69.49","url":"https://i.ebayimg.com/thumbs/images/g/lkYAAOSwq5dcixV3/s-l800.webp","shipping":"+RMB 11.65 shipping","source_url":"https://www.ebay.com/itm/383672834260?hash=item5954aed8d4:g:lkYAAOSwq5dcixV3"},{"title":"2pcs LED Car Door Welcome Light Projector Lamp Logo For MINI Cooper R50 R53 R55","price":"RMB 90.10","url":"https://i.ebayimg.com/thumbs/images/g/nF4AAOSwKlddhYvz/s-l800.webp","shipping":"Free International Shipping","source_url":"https://www.ebay.com/itm/275293579878?hash=item4018c6aa66:g:nF4AAOSwKlddhYvz"},{"title":"Sheepskin Wool Fur Car Seat Cover Waist Cushion Neck Pillow Universal","price":"RMB 728.92","url":"https://i.ebayimg.com/thumbs/images/g/klYAAOSwB7lfZG0N/s-l800.webp","shipping":"Free International Shipping","source_url":"https://www.ebay.com/itm/264852328238?hash=item3daa6dcf2e:g:klYAAOSwB7lfZG0N"},{"title":"Men's Slimming Body Shaper Gym Workout Vest Abdomen Compression Shirt Tank Tops","price":"RMB 74.53 to RMB 120.38","url":"https://i.ebayimg.com/thumbs/images/g/RskAAOSwhctguGZL/s-l800.webp","shipping":"Free International Shipping","source_url":"https://www.ebay.com/itm/154478192376?hash=item23f79e26f8:g:RskAAOSwhctguGZL"},{"title":"SURPLUS CHINESE CHINA ARMY PLA LEATHER SKS SOLDIER SLING MILITARY","price":"RMB 86.83","url":"https://i.ebayimg.com/thumbs/images/g/-GAAAOSw7bpbnmwa/s-l800.webp","shipping":"+RMB 13.37 shipping","source_url":"https://www.ebay.com/itm/193356678131?hash=item2d04f4c3f3:g:-GAAAOSw7bpbnmwa"},{"title":"78mm VIB Bait Fishing Lure Pike Perch Lure Hard Bait Sinking For Pike Perch Bass","price":"RMB 20.65","url":"https://i.ebayimg.com/thumbs/images/g/1B0AAOSwTpVhhPoh/s-l800.webp","shipping":"+RMB 26.67 shipping","source_url":"https://www.ebay.com/itm/154694038385?hash=item24047bb371:g:1B0AAOSwTpVhhPoh"},{"title":"Sand 24\"x36\" HD Canvas Poster Decor Wall Art Prints Card Tube Packing","price":"RMB 90.84","url":"https://i.ebayimg.com/thumbs/images/g/7vYAAOSwaTpimDtz/s-l800.webp","shipping":"Free International Shipping","source_url":"https://www.ebay.com/itm/374109596849?hash=item571aab6cb1:g:7vYAAOSwaTpimDtz"},{"title":"30pcs Bumper Moulding Clips Retainer Fastener For Toyota Land Cruiser 2008-2016","price":"RMB 53.14","url":"https://i.ebayimg.com/thumbs/images/g/vOwAAOSwv2FfhR76/s-l800.webp","shipping":"Free International Shipping","source_url":"https://www.ebay.com/itm/332779509743?hash=item4d7b3457ef:g:vOwAAOSwv2FfhR76"},{"title":"Natural Asian Green Rare Crystal Quartz Stone Healing Gemstone Sphere Decor 40mm","price":"RMB 72.79","url":"https://i.ebayimg.com/thumbs/images/g/WwEAAOSwWu9idnHT/s-l800.webp","shipping":"Free International Shipping","source_url":"https://www.ebay.com/itm/304478403418?hash=item46e453bb5a:g:WwEAAOSwWu9idnHT"},{"title":"Diptera mosquito fly Burmite Myanmar Burmese Amber insect fossil dinosaur age","price":"RMB 15.04","url":"https://i.ebayimg.com/thumbs/images/g/rAwAAOSw00BimggZ/s-l800.webp","shipping":"Free International Shipping","source_url":"https://www.ebay.com/itm/265720861499?hash=item3dde32933b:g:rAwAAOSw00BimggZ"},{"title":"Elegant Cubic Zircon Stud Earrings 925 Silver Women Wedding Jewelry A Pair/set","price":"RMB 14.55","url":"https://i.ebayimg.com/thumbs/images/g/XDIAAOSwbMlg941x/s-l800.webp","shipping":"Free International Shipping","source_url":"https://www.ebay.com/itm/133824861080?hash=item1f28955398:g:XDIAAOSwbMlg941x"},{"title":"Women Sexy Bra Vest Lace Seamless Push Up Top Underwear Breathable Solid","price":"RMB 8.41 to RMB 21.11","url":"https://i.ebayimg.com/thumbs/images/g/QygAAOSwvH5dLsSu/s-l800.webp","shipping":"Free International Shipping","source_url":"https://www.ebay.com/itm/392800195779?hash=item5b74b754c3:g:QygAAOSwvH5dLsSu"},{"title":"5 x Banjo Geared Gear Ratio 4:1 Tuner Tuning Keys Peg Machine Heads Chrome","price":"RMB 180.81","url":"https://i.ebayimg.com/thumbs/images/g/ZZMAAOSwauZiVBbe/s-l800.webp","shipping":"+RMB 5.35 shipping","source_url":"https://www.ebay.com/itm/403428908546?hash=item5dee3c9e02:g:ZZMAAOSwauZiVBbe"},{"title":"Radiator Fan Switch Sensor For Kawasaki Prairie 400 650 700 KVF Brute Force 650","price":"RMB 91.91","url":"https://i.ebayimg.com/thumbs/images/g/AC4AAOSwWW5imtrb/s-l800.webp","shipping":"Free International Shipping","source_url":"https://www.ebay.com/itm/284842774244?hash=item4251f3cee4:g:AC4AAOSwWW5imtrb"},{"title":"Silicone Radiator Hose Fit Mazda Roadstar Miata MX-5 NA6CE B6ZE 1.6L 89-93 Teal","price":"RMB 461.21","url":"https://i.ebayimg.com/thumbs/images/g/QzYAAOSwfftii6hD/s-l800.webp","shipping":"Free International Shipping","source_url":"https://www.ebay.com/itm/304499600714?hash=item46e5972d4a:g:QzYAAOSwfftii6hD"},{"title":"FOR HP Probook 6560B 6565B 6570B 6575B 8570P 8560P Keyboard Latin Spanish Point","price":"RMB 84.82","url":"https://i.ebayimg.com/thumbs/images/g/yH0AAOSwlHRfr6Fy/s-l800.webp","shipping":"+RMB 50.13 shipping","source_url":"https://www.ebay.com/itm/224234192363?hash=item3435663deb:g:yH0AAOSwlHRfr6Fy"},{"title":"Men Sexy Mesh Underwear Boxer Briefs Shorts Underpants Summer Fishnet Hollow","price":"RMB 48.20 to RMB 49.37","url":"https://i.ebayimg.com/thumbs/images/g/o8wAAOSwIDximJc1/s-l800.webp","shipping":"Free International Shipping","source_url":"https://www.ebay.com/itm/225014114982?hash=item3463e2eaa6:g:o8wAAOSwIDximJc1"},{"title":"ABS Chrome Interior Seat Side Frame Trim For BMW X1 F48 2016-2021 2pcs","price":"RMB 113.03","url":"https://i.ebayimg.com/thumbs/images/g/pmMAAOSwbXBaEpRv/s-l800.webp","shipping":"+RMB 26.60 shipping","source_url":"https://www.ebay.com/itm/353023832226?hash=item5231dc30a2:g:pmMAAOSwbXBaEpRv"},{"title":"Cartoon Princess Dress BabyShark Kids Sleeveless Ruffle Twirl Girls Dress Size","price":"RMB 125.60","url":"https://i.ebayimg.com/thumbs/images/g/orAAAOSwhX5iDLcU/s-l800.webp","shipping":"Free International Shipping","source_url":"https://www.ebay.com/itm/403548408525?hash=item5df55c0acd:g:orAAAOSwhX5iDLcU"},{"title":"Men Thongs G Strings T-Back Sexy Briefs Underwear Seamless Sissy Shorts Ice Silk","price":"RMB 33.12","url":"https://i.ebayimg.com/thumbs/images/g/p~IAAOSwUaJh4mMH/s-l800.webp","shipping":"+RMB 15.82 shipping","source_url":"https://www.ebay.com/itm/403411558452?hash=item5ded33e034:g:p~IAAOSwUaJh4mMH"},{"title":"5pcs natural Auspicious Jade hand carved crystal mushroom reiki healing gems","price":"RMB 21.32","url":"https://i.ebayimg.com/thumbs/images/g/3i8AAOSwd6Fimgfl/s-l800.webp","shipping":"Free International Shipping","source_url":"https://www.ebay.com/itm/314022403901?hash=item491d319f3d:g:3i8AAOSwd6Fimgfl"},{"title":"Stylus Pen Replacement For LG Stylo 5 4 3 / 3 Plus / G4 / Q710 Q720 LS777!","price":"RMB 19.65 to RMB 23.26","url":"https://i.ebayimg.com/thumbs/images/g/q7kAAOSwc3Rgd~9l/s-l800.webp","shipping":"Free International Shipping","source_url":"https://www.ebay.com/itm/353457507729?hash=item524bb58d91:g:q7kAAOSwc3Rgd~9l"},{"title":"MUSTANG W/ Flag Tire Lettering Permanent Sticker 1.06\" 14\"-22\" 8 Sets Decal","price":"RMB 124.26","url":"https://i.ebayimg.com/thumbs/images/g/gloAAOSwQjthOsKL/s-l800.webp","shipping":"+RMB 10.03 shipping","source_url":"https://www.ebay.com/itm/154604516403?hash=item23ff25b433:g:gloAAOSwQjthOsKL"},{"title":"Wooden Musical Tambourine Double Row 10inch Instrument Hand Drum Educational Toy","price":"RMB 76.07","url":"https://i.ebayimg.com/thumbs/images/g/yOsAAOSwP3Fgi23J/s-l800.webp","shipping":"Free International Shipping","source_url":"https://www.ebay.com/itm/224443336977?hash=item3441dd8911:g:yOsAAOSwP3Fgi23J"},{"title":"Realtek Mini USB Wireless 802.11B/G/N LAN Card WiFi Network Adapter RTL8188","price":"RMB 13.30","url":"https://i.ebayimg.com/thumbs/images/g/rgsAAOSwGExifGff/s-l800.webp","shipping":"Free International Shipping","source_url":"https://www.ebay.com/itm/403653650060?hash=item5dfba1e68c:g:rgsAAOSwGExifGff"},{"title":"Front Bumper Fog Light Lamp Deco Trim For Ford Focus RS 2016 2017 2018 Black DN","price":"RMB 627.99","url":"https://i.ebayimg.com/thumbs/images/g/vkQAAOSwRTpileKj/s-l800.webp","shipping":"Free International Shipping","source_url":"https://www.ebay.com/itm/383799554738?hash=item595c3c72b2:g:vkQAAOSwRTpileKj"},{"title":"Oil Pressure Switch Sensor for Bobcat Skid Steer Loader 751 753 763 773 6670705","price":"RMB 280.67","url":"https://i.ebayimg.com/thumbs/images/g/zGIAAOSwaM1huFmW/s-l800.webp","shipping":"Free International Shipping","source_url":"https://www.ebay.com/itm/165232760122?hash=item2678a3d53a:g:zGIAAOSwaM1huFmW"},{"title":"Car Fuel Heater A/C Line Fuel Pipe Quick Removal Disconnect Tool Chrome Metal","price":"RMB 111.03","url":"https://i.ebayimg.com/thumbs/images/g/cbMAAOSw3olf79iY/s-l800.webp","shipping":"Free International Shipping","source_url":"https://www.ebay.com/itm/203836076758?hash=item2f7593b2d6:g:cbMAAOSw3olf79iY"},{"title":"1Pcs Car Exhaust Pipe Tip Muffler Steel Stainless Trim Tail Tube Stainless Steel","price":"RMB 202.53","url":"https://i.ebayimg.com/thumbs/images/g/mJkAAOSwlsFil15j/s-l800.webp","shipping":"Free International Shipping","source_url":"https://www.ebay.com/itm/394099061942?hash=item5bc22274b6:g:mJkAAOSwlsFil15j"},{"title":"Bohemian Handmade Women 925 Silver Turquoise Drop Dangle Vintage Earrings Hook","price":"RMB 6.61","url":"https://i.ebayimg.com/thumbs/images/g/FIMAAOSwVYpinKrv/s-l800.webp","shipping":"Free International Shipping","source_url":"https://www.ebay.com/itm/384932347136?hash=item599fc17d00:g:FIMAAOSwVYpinKrv"},{"title":"Case for iPhone 11 12 13 Pro Max Mini 7 8 SE XR XS Clear Shockproof Phone Cover","price":"RMB 20.87 to RMB 30.93","url":"https://i.ebayimg.com/thumbs/images/g/TTMAAOSwTjtiIG1K/s-l800.webp","shipping":"+RMB 25.06 shipping","source_url":"https://www.ebay.com/itm/284679209359?hash=item424834018f:g:TTMAAOSwTjtiIG1K"},{"title":"Big Blue Sapphire Water Drop CZ Pendant Jewelry Women Necklace Earrings Set","price":"RMB 66.58","url":"https://i.ebayimg.com/thumbs/images/g/bWgAAOSwmBhiOXQ~/s-l800.webp","shipping":"Free International Shipping","source_url":"https://www.ebay.com/itm/394000316047?hash=item5bbc3fb68f:g:bWgAAOSwmBhiOXQ~"},{"title":"Pink Sapphire Jewelry Set for Women Round Big CZ Crystal Rings Earrings Necklace","price":"RMB 65.17","url":"https://i.ebayimg.com/thumbs/images/g/xI4AAOSwObpiezRG/s-l800.webp","shipping":"Free International Shipping","source_url":"https://www.ebay.com/itm/394069340316?hash=item5bc05cf09c:g:xI4AAOSwObpiezRG"},{"title":"Womens T-Shirt Tank Shiny Satin Glossy Opaque Tops Summer Blouse Soft Round-Neck","price":"RMB 144.98","url":"https://i.ebayimg.com/thumbs/images/g/me8AAOSwQQxiRDOq/s-l800.webp","shipping":"+RMB 52.14 shipping","source_url":"https://www.ebay.com/itm/325124622081?hash=item4bb2f00701:g:me8AAOSwQQxiRDOq"},{"title":"New 40mm Yellow Mexican Opal Sphere,Crystal Ball/Gemstone","price":"RMB 21.92","url":"https://i.ebayimg.com/thumbs/images/g/U7gAAOSwkNZUbAX9/s-l800.webp","shipping":"Free International Shipping","source_url":"https://www.ebay.com/itm/314024981041?hash=item491d58f231:g:U7gAAOSwkNZUbAX9"},{"title":"Women Bodycon Dresses Pencil Skirt Sexy Wetlook Stretch Shiny Glossy Comfort 3XL","price":"RMB 174.39","url":"https://i.ebayimg.com/thumbs/images/g/P7IAAOSwrXFhNxY8/s-l800.webp","shipping":"+RMB 46.72 shipping","source_url":"https://www.ebay.com/itm/324780289279?hash=item4b9e69ecff:g:P7IAAOSwrXFhNxY8"},{"title":"Minimizer Bras Plus Size Lace Bra Women Unlined Full Coverage Wireless Plus Size","price":"RMB 79.94","url":"https://i.ebayimg.com/thumbs/images/g/cmYAAOSwTOxhUvpe/s-l800.webp","shipping":"+RMB 13.30 shipping","source_url":"https://www.ebay.com/itm/124923668315?hash=item1d1607e75b:g:cmYAAOSwTOxhUvpe"},{"title":"38mm 40MM black PVD Watch Case ceramic bezel sapphire fit NH35 NH36 2824 PT5000","price":"RMB 318.84","url":"https://i.ebayimg.com/thumbs/images/g/ui8AAOSwMYZh3QFi/s-l800.webp","shipping":"Free International Shipping","source_url":"https://www.ebay.com/itm/115184240098?hash=item1ad18405e2:g:ui8AAOSwMYZh3QFi"},{"title":"Gothic Case For iPhone 13 12 11 Pro Max Mini XR XS SE 8 7 6Plus Skull Soft Cover","price":"RMB 59.82 to RMB 66.51","url":"https://i.ebayimg.com/thumbs/images/g/VSYAAOSw63RiA4~G/s-l800.webp","shipping":"Free International Shipping","source_url":"https://www.ebay.com/itm/224829982121?hash=item3458e945a9:g:VSYAAOSw63RiA4~G"},{"title":"Womens Casual Round Neck T Shirt Short Sleeve Printed Tees Tops Pullover S-5XL","price":"RMB 31.15 to RMB 83.49","url":"https://i.ebayimg.com/thumbs/images/g/pXAAAOSwAEJiLtot/s-l800.webp","shipping":"Free International Shipping","source_url":"https://www.ebay.com/itm/394020425528?hash=item5bbd728f38:g:pXAAAOSwAEJiLtot"},{"title":"26\" Telescopic Stick Whip Portable Pocket Baton Retractable Outdoor Tool","price":"RMB 171.38","url":"https://i.ebayimg.com/thumbs/images/g/NSIAAOSwuN1f-7Vd/s-l800.webp","shipping":"+RMB 66.78 shipping","source_url":"https://www.ebay.com/itm/403532730560?hash=item5df46cd0c0:g:NSIAAOSwuN1f-7Vd"},{"title":"Sexy Men's See-through Boxer Briefs Sheer Mesh Pouch Underwear Panties Lingerie","price":"RMB 19.92","url":"https://i.ebayimg.com/thumbs/images/g/ixkAAOSw8U1bcsbB/s-l800.webp","shipping":"+RMB 19.99 shipping","source_url":"https://www.ebay.com/itm/192627246252?hash=item2cd97a84ac:g:ixkAAOSw8U1bcsbB"},{"title":"Silicone Sink Faucet Splash Guard for Kitchen Sink Bathroom With Drainage Edge","price":"RMB 79.28","url":"https://i.ebayimg.com/thumbs/images/g/vAkAAOSwurBiPX3b/s-l800.webp","shipping":"Free International Shipping","source_url":"https://www.ebay.com/itm/384803258023?hash=item59980fbea7:g:vAkAAOSwurBiPX3b"},{"title":"Vintage Men Cufflinks Jewelry Rhinestone Classic Black Cuff Links Tie Clasps New","price":"RMB 56.75","url":"https://i.ebayimg.com/thumbs/images/g/glUAAOSw4bhibPgm/s-l800.webp","shipping":"Free International Shipping","source_url":"https://www.ebay.com/itm/354036084216?hash=item526e31edf8:g:glUAAOSw4bhibPgm"},{"title":"Interior Full Set Decor Cover Trim Accessories For Jeep Wrangler JK JKU 2011-17","price":"RMB 361.35","url":"https://i.ebayimg.com/thumbs/images/g/ivgAAOSwcqlhcnW~/s-l800.webp","shipping":"Free International Shipping","source_url":"https://www.ebay.com/itm/234249785253?hash=item368a600fa5:g:ivgAAOSwcqlhcnW~"},{"title":"CNC Front Brake Oil Fluid Reservoir Cover For SUZUKI DRZ400S/DR-Z 400E/DRZ 400SM","price":"RMB 66.78","url":"https://i.ebayimg.com/thumbs/images/g/iMsAAOSwg3hhkJkF/s-l800.webp","shipping":"Free International Shipping","source_url":"https://www.ebay.com/itm/234285729133?hash=item368c84856d:g:iMsAAOSwg3hhkJkF"},{"title":"for Yamaha Tenere700 Tenere 700 2019-2021 Headlight Guard Grill Protector Cover","price":"RMB 139.63","url":"https://i.ebayimg.com/thumbs/images/g/8xoAAOSwoNJhpckS/s-l800.webp","shipping":"+RMB 36.76 shipping","source_url":"https://www.ebay.com/itm/175087341545?hash=item28c404cfe9:g:8xoAAOSwoNJhpckS"},{"title":"34\" 35\" Car Spare Wheel Tire Covers Heavy Duty Vinyl For Hummer H2 Silver Logo","price":"RMB 260.69","url":"https://i.ebayimg.com/thumbs/images/g/yi4AAOSwvEphm4xw/s-l800.webp","shipping":"Free International Shipping","source_url":"https://www.ebay.com/itm/403496155872?hash=item5df23ebae0:g:yi4AAOSwvEphm4xw"},{"title":"Tail Tidy Fender Eliminator LED Brake Light For SUZUKI DR-Z 400SM DRZ400 S/SM US","price":"RMB 135.22 to RMB 152.87","url":"https://i.ebayimg.com/thumbs/images/g/RXUAAOSw5d9fetTZ/s-l800.webp","shipping":"Free International Shipping","source_url":"https://www.ebay.com/itm/134048463078?hash=item1f35e938e6:g:RXUAAOSw5d9fetTZ"},{"title":"Luxury Meisterstuck Black+Silver Clip Ballpoint Pen 0.7mm Medium Quality Pen","price":"RMB 133.69","url":"https://i.ebayimg.com/thumbs/images/g/VaIAAOSwbaVif5KL/s-l800.webp","shipping":"Free International Shipping","source_url":"https://www.ebay.com/itm/234552164568?hash=item369c6600d8:g:VaIAAOSwbaVif5KL"},{"title":"3\" Natural Golden Obsidian snake Carved Quartz Crystal Skull Reiki Healing 1pc","price":"RMB 149.63","url":"https://i.ebayimg.com/thumbs/images/g/5YIAAOSwbvlg9ZDt/s-l800.webp","shipping":"Free International Shipping","source_url":"https://www.ebay.com/itm/164967391451?hash=item2668d2a0db:g:5YIAAOSwbvlg9ZDt"},{"title":"Classic Luxury Peacock Bird Gold Tone Brooch Pin Purple Rhinestone Crystal","price":"RMB 98.39","url":"https://i.ebayimg.com/thumbs/images/g/72UAAOSwxTlZyw--/s-l800.webp","shipping":"+RMB 13.37 shipping","source_url":"https://www.ebay.com/itm/282670847619?hash=item41d07ed683:g:72UAAOSwxTlZyw--"},{"title":"Princess Pink Super Cute Kawaii Cartoons Folding Kitchen Paring Knife Pocket","price":"RMB 106.88","url":"https://i.ebayimg.com/thumbs/images/g/3zIAAOSwXPxiICvk/s-l800.webp","shipping":"Free International Shipping","source_url":"https://www.ebay.com/itm/313898270053?hash=item4915cb7d65:g:3zIAAOSwXPxiICvk"},{"title":"Elegant colorful crystal Rhinestone flower leaf brooch pin Pendant","price":"RMB 91.04","url":"https://i.ebayimg.com/thumbs/images/g/L-MAAMXQuCdTh1x8/s-l800.webp","shipping":"+RMB 13.37 shipping","source_url":"https://www.ebay.com/itm/271559890074?hash=item3f3a3b149a:g:L-MAAMXQuCdTh1x8"},{"title":"Art Nouveau Peacock Brooch Pins Vintage Style Green Crystal Rhinestone Pendant","price":"RMB 96.05","url":"https://i.ebayimg.com/thumbs/images/g/OucAAMXQNo5TYTDJ/s-l800.webp","shipping":"+RMB 13.37 shipping","source_url":"https://www.ebay.com/itm/281370145837?hash=item4182f7b42d:g:OucAAMXQNo5TYTDJ"},{"title":"Vintage Green Rose Flower Pendant Woman's Brooch Pin Crystal Rhinestone Gifts","price":"RMB 71.86","url":"https://i.ebayimg.com/thumbs/images/g/N2AAAOSwhxJhwRoW/s-l800.webp","shipping":"+RMB 13.37 shipping","source_url":"https://www.ebay.com/itm/284576628940?hash=item424216c0cc:g:N2AAAOSwhxJhwRoW"},{"title":"Vintage 3 Butterfly Pendant Woman Brooch Pin Multi-color Rhinestone Crystal","price":"RMB 75.47","url":"https://i.ebayimg.com/thumbs/images/g/O5EAAOSwEM1hypQ~/s-l800.webp","shipping":"+RMB 13.37 shipping","source_url":"https://www.ebay.com/itm/284585399384?hash=item42429c9458:g:O5EAAOSwEM1hypQ~"},{"title":"Gynecomastia Firming Ginger Cream Ginger Abdominal Cream Men's And Women's","price":"RMB 51.13","url":"https://i.ebayimg.com/thumbs/images/g/mOMAAOSwoBxiciuf/s-l800.webp","shipping":"Free International Shipping","source_url":"https://www.ebay.com/itm/394058836077?hash=item5bbfbca86d:g:mOMAAOSwoBxiciuf"},{"title":"100Pcs 16-14AWG 1/4\" 90° Right Flag Female Spade Terminal Connector Insulated KD","price":"RMB 47.39","url":"https://i.ebayimg.com/thumbs/images/g/JoMAAOSwx41iByIH/s-l800.webp","shipping":"+RMB 19.99 shipping","source_url":"https://www.ebay.com/itm/312372394762?hash=item48bad87b0a:g:JoMAAOSwx41iByIH"},{"title":"32\" 33\" Car Spare Wheel Tire Covers Heavy Duty Vinyl For Hummer H3 Silver Logo","price":"RMB 233.15","url":"https://i.ebayimg.com/thumbs/images/g/uJEAAOSwLv1hm4vG/s-l800.webp","shipping":"Free International Shipping","source_url":"https://www.ebay.com/itm/403496155873?hash=item5df23ebae1:g:uJEAAOSwLv1hm4vG"},{"title":"Steering Column Bearing Kit Iron Fit for Ford Mercury Lincoln 1992 up","price":"RMB 125.26","url":"https://i.ebayimg.com/thumbs/images/g/fK8AAOSwfmxiALcd/s-l800.webp","shipping":"Free International Shipping","source_url":"https://www.ebay.com/itm/313865669708?hash=item4913da0c4c:g:fK8AAOSwfmxiALcd"},{"title":"MAX3232 RS232 to TTL Serial Port Converter Module DB9 Connector M32","price":"RMB 14.84","url":"https://i.ebayimg.com/thumbs/images/g/rBsAAOSw8cNUNc6J/s-l800.webp","shipping":"+RMB 24.00 shipping","source_url":"https://www.ebay.com/itm/373769611482?hash=item570667a8da:g:rBsAAOSw8cNUNc6J"},{"title":"500Pcs Female Thread Brass Knurled Threaded Insert Embedment Nuts Assortment Kit","price":"RMB 83.49 to RMB 108.89","url":"https://i.ebayimg.com/thumbs/images/g/uwUAAOSwZClhxC9H/s-l800.webp","shipping":"+RMB 16.68 shipping","source_url":"https://www.ebay.com/itm/403371803478?hash=item5dead54356:g:uwUAAOSwZClhxC9H"},{"title":"COWL LOCK HATCH CLIPS TURN type rc boat gas nitro aluminium GOLD/RED/SILVER/BLUE","price":"RMB 60.16","url":"https://i.ebayimg.com/thumbs/images/g/Aa8AAOSwKphcHE8y/s-l800.webp","shipping":"+RMB 46.79 shipping","source_url":"https://www.ebay.com/itm/224910324612?hash=item345db33384:g:Aa8AAOSwKphcHE8y"},{"title":"For Cadillac XT5 2017-2022 Chrome Steel Rear Window Side Spoiler Cover Trim 2PCS","price":"RMB 174.99","url":"https://i.ebayimg.com/thumbs/images/g/pWcAAOSw6uFiS2Xv/s-l800.webp","shipping":"Free International Shipping","source_url":"https://www.ebay.com/itm/194956879041?hash=item2d6455e4c1:g:pWcAAOSw6uFiS2Xv"},{"title":"30\" 31\" Car Spare Wheel Tire Covers Bag Protector Heavy Duty Vinyl For Hummer H3","price":"RMB 233.15","url":"https://i.ebayimg.com/thumbs/images/g/ZRkAAOSwiI5hk6Gf/s-l800.webp","shipping":"Free International Shipping","source_url":"https://www.ebay.com/itm/403496155877?hash=item5df23ebae5:g:ZRkAAOSwiI5hk6Gf"},{"title":"100 pcs Prepared Glass Microscope Slides for Student Science Research Learning","price":"RMB 249.46","url":"https://i.ebayimg.com/thumbs/images/g/ProAAOSwCKpgniAs/s-l800.webp","shipping":"+RMB 33.42 shipping","source_url":"https://www.ebay.com/itm/273473052981?hash=item3fac43a135:g:ProAAOSwCKpgniAs"},{"title":"1997-2006 DBC LS1 STAND ALONE HARNESS 4L60E 4.8 5.3 6.0 VORTEC DRIVE BY CABLE","price":"RMB 1,154.04","url":"https://i.ebayimg.com/thumbs/images/g/V34AAOSw-AZhmwrz/s-l800.webp","shipping":"Free International Shipping","source_url":"https://www.ebay.com/itm/393690616100?hash=item5ba9ca1124:g:V34AAOSw-AZhmwrz"},{"title":"Turn Signal Indicator For Yamaha YZF R1 R3 R6 R15 YZF600R YZF750R FZR600 TRX850","price":"RMB 133.55","url":"https://i.ebayimg.com/thumbs/images/g/6XsAAOSwn8BiJM~u/s-l800.webp","shipping":"Free International Shipping","source_url":"https://www.ebay.com/itm/334354262167?hash=item4dd9112897:g:6XsAAOSwn8BiJM~u"},{"title":"1/10 LED Lights RC Car Lampshade for Tamiya Holiday Buggy Monster SCX10 D90 H2U","price":"RMB 84.69 to RMB 107.48","url":"https://i.ebayimg.com/thumbs/images/g/mfwAAOSwktViXN~a/s-l800.webp","shipping":"Free International Shipping","source_url":"https://www.ebay.com/itm/275276333701?hash=item4017bf8285:g:mfwAAOSwktViXN~a"},{"title":"unique unknown fly bug Burmite Myanmar Burmese Amber insect fossil dinosaur age","price":"RMB 8.69","url":"https://i.ebayimg.com/thumbs/images/g/0JsAAOSwFedimgeG/s-l800.webp","shipping":"Free International Shipping","source_url":"https://www.ebay.com/itm/265720859053?hash=item3dde3289ad:g:0JsAAOSwFedimgeG"},{"title":"New Find Yellow Phantom Quartz Citrine Crystal Cluster Mineral Specimen Healing","price":"RMB 353.20","url":"https://i.ebayimg.com/thumbs/images/g/IIcAAOSwR1pin3Mu/s-l800.webp","shipping":"Free International Shipping","source_url":"https://www.ebay.com/itm/134141135327?hash=item1f3b6f49df:g:IIcAAOSwR1pin3Mu"},{"title":"Steel Built-In Door Sill Scuff Bar Protection Plate Trim For Hummer H2 2003-2009","price":"RMB 1,604.16","url":"https://i.ebayimg.com/thumbs/images/g/TdoAAOSwiSRikIY3/s-l800.webp","shipping":"Free International Shipping","source_url":"https://www.ebay.com/itm/284831665359?hash=item42514a4ccf:g:TdoAAOSwiSRikIY3"},{"title":"Rare 36.3G Natural Agate Geode Quartz Crystal Mineral Specimen Healing W060307","price":"RMB 25.40","url":"https://i.ebayimg.com/thumbs/images/g/lwYAAOSwqw1imgdj/s-l800.webp","shipping":"Free International Shipping","source_url":"https://www.ebay.com/itm/125349610498?hash=item1d2f6b4402:g:lwYAAOSwqw1imgdj"},{"title":"4Pcs Razer Purple Optical Switches Hot Swap Switch for Razer Huntsman Elite","price":"RMB 25.60","url":"https://i.ebayimg.com/thumbs/images/g/r6cAAOSw~0RiV1hb/s-l800.webp","shipping":"+RMB 28.61 shipping","source_url":"https://www.ebay.com/itm/354007940373?hash=item526c847d15:g:r6cAAOSw~0RiV1hb"},{"title":"3.5mm Desktop Capacitive Microphone Audio Recording For Computer Desktop A8M1","price":"RMB 55.88","url":"https://i.ebayimg.com/thumbs/images/g/qqQAAOSwlCliBht0/s-l800.webp","shipping":"Free International Shipping","source_url":"https://www.ebay.com/itm/363731028464?hash=item54b00f09f0:g:qqQAAOSwlCliBht0"},{"title":"Fashion 925 Silver Cubic Zirconia Red Heart Zircon Earrings Anniversary Gift","price":"RMB 14.10","url":"https://i.ebayimg.com/thumbs/images/g/czUAAOSw5bRileBD/s-l800.webp","shipping":"+RMB 19.99 shipping","source_url":"https://www.ebay.com/itm/363857339527?hash=item54b7966487:g:czUAAOSw5bRileBD"},{"title":"925 Silver Filled Women Planet Droplets Zircon Earrings Wedding AnniversaryGift","price":"RMB 14.57","url":"https://i.ebayimg.com/thumbs/images/g/6CAAAOSwcrdilI0W/s-l800.webp","shipping":"+RMB 19.99 shipping","source_url":"https://www.ebay.com/itm/363856054250?hash=item54b782c7ea:g:6CAAAOSwcrdilI0W"},{"title":"Fashion 925 Silver Cubic Zirconia Starburst Zircon Earrings Anniversary Gift","price":"RMB 14.50","url":"https://i.ebayimg.com/thumbs/images/g/16UAAOSwt9FileBI/s-l800.webp","shipping":"+RMB 19.99 shipping","source_url":"https://www.ebay.com/itm/363857339559?hash=item54b79664a7:g:16UAAOSwt9FileBI"},{"title":"Emergency Capless Fuel Fill Filler Funnel Spout Adapter White For Ford Lincoln","price":"RMB 50.73","url":"https://i.ebayimg.com/thumbs/images/g/hNUAAOSwkUJf4tfP/s-l800.webp","shipping":"Free International Shipping","source_url":"https://www.ebay.com/itm/174569362417?hash=item28a52513f1:g:hNUAAOSwkUJf4tfP"},{"title":"New Classic Checks Pink White JACQUARD WOVEN 100% Silk Men's Tie Necktie","price":"RMB 60.09","url":"https://i.ebayimg.com/thumbs/images/g/qiMAAOSw2n9iQ8Ct/s-l800.webp","shipping":"Free International Shipping","source_url":"https://www.ebay.com/itm/255462019753?hash=item3b7ab912a9:g:qiMAAOSw2n9iQ8Ct"},{"title":"New Classic Checks Sky Blue Gray Dark Blue JACQUARD WOVEN Silk Men's Tie Necktie","price":"RMB 60.09","url":"https://i.ebayimg.com/thumbs/images/g/EJkAAOSwz2tZmPUS/s-l800.webp","shipping":"Free International Shipping","source_url":"https://www.ebay.com/itm/255532120889?hash=item3b7ee6bb39:g:EJkAAOSwz2tZmPUS"},{"title":"New Classic Checks Gold White JACQUARD WOVEN Silk Men's Tie Necktie","price":"RMB 60.09","url":"https://i.ebayimg.com/thumbs/images/g/o1sAAOSwYY9iNKOI/s-l800.webp","shipping":"Free International Shipping","source_url":"https://www.ebay.com/itm/255541550275?hash=item3b7f769cc3:g:o1sAAOSwYY9iNKOI"},{"title":"New Classic Checks Gray Blue Red Purple JACQUARD WOVEN Silk Men's Tie Necktie","price":"RMB 60.09","url":"https://i.ebayimg.com/thumbs/images/g/gRcAAOSwCkZZVaaC/s-l800.webp","shipping":"Free International Shipping","source_url":"https://www.ebay.com/itm/265275999062?hash=item3dc3ae8356:g:gRcAAOSwCkZZVaaC"},{"title":"0HFXN4 PM41V HFXN4 Replace USB-C Cable For Dell Dock WD15 K17A K17A001 length:1M","price":"RMB 213.90","url":"https://i.ebayimg.com/thumbs/images/g/L6UAAOSw-I1iWAy0/s-l800.webp","shipping":"+RMB 26.74 shipping","source_url":"https://www.ebay.com/itm/384834398923?epid=8026686002&hash=item5999eaeacb:g:L6UAAOSw-I1iWAy0"},{"title":"Baofeng Walkie Talkie AR-152 Tactical Dual Band Long Range Ham Two Way Radio","price":"RMB 659.67","url":"https://i.ebayimg.com/thumbs/images/g/bRUAAOSwXnBiFY~a/s-l800.webp","shipping":"Free International Shipping","source_url":"https://www.ebay.com/itm/393951584497?hash=item5bb95820f1:g:bRUAAOSwXnBiFY~a"},{"title":"Rear Back Battery Cover Case Door Housing Sticker for Xiaomi Mi 10t Pro 5G Black","price":"RMB 74.86","url":"https://i.ebayimg.com/thumbs/images/g/L1kAAOSwZ~hhH1Yu/s-l800.webp","shipping":"Free International Shipping","source_url":"https://www.ebay.com/itm/185007497250?hash=item2b134e6022:g:L1kAAOSwZ~hhH1Yu"},{"title":"C/D/DD/F/G/H/I Women Full Coverage Underwire Push Up Bra Lace Plus Size Bralette","price":"RMB 79.88","url":"https://i.ebayimg.com/thumbs/images/g/BYkAAOSwJG5f4sVA/s-l800.webp","shipping":"+RMB 13.23 shipping","source_url":"https://www.ebay.com/itm/193818481578?hash=item2d207b53aa:g:BYkAAOSwJG5f4sVA"},{"title":"Basketball Arcade ESPN Hoops Game 2-Player EZ-Fold LED Score Sturdy Easy Storage","price":"RMB 393.37","url":"https://i.ebayimg.com/thumbs/images/g/~iUAAOSw-iVigcFB/s-l800.webp","shipping":"Free International Shipping","source_url":"https://www.ebay.com/itm/363840419719?hash=item54b6943787:g:~iUAAOSw-iVigcFB"},{"title":"5pcs G9 Light Socket Rings Lamp Shade Holder Adapter Ring Light Fixtures White","price":"RMB 30.35","url":"https://i.ebayimg.com/thumbs/images/g/6DkAAOSwTHNiTn4Z/s-l800.webp","shipping":"+RMB 25.15 shipping","source_url":"https://www.ebay.com/itm/363752230055?hash=item54b1528ca7:g:6DkAAOSwTHNiTn4Z"},{"title":"30\" 31\" Car Spare Wheel Tire Covers Hummer H3 Heavy Duty Vinyl PU Leather R16","price":"RMB 240.50","url":"https://i.ebayimg.com/thumbs/images/g/EQ4AAOSwgCJhXHEm/s-l800.webp","shipping":"Free International Shipping","source_url":"https://www.ebay.com/itm/353708281241?hash=item525aa80d99:g:EQ4AAOSwgCJhXHEm"},{"title":"32\" 33\" Car Spare Wheel Tire Covers Hummer H3 Heavy Duty Vinyl PU Leather R17","price":"RMB 240.50","url":"https://i.ebayimg.com/thumbs/images/g/EQ4AAOSwgCJhXHEm/s-l800.webp","shipping":"Free International Shipping","source_url":"https://www.ebay.com/itm/353708283567?hash=item525aa816af:g:EQ4AAOSwgCJhXHEm"},{"title":"34\" 35\" Car Spare Wheel Tire Covers Hummer H2 Silver Heavy Duty Vinyl PU Leather","price":"RMB 253.87","url":"https://i.ebayimg.com/thumbs/images/g/J2UAAOSwEgVhXHKz/s-l800.webp","shipping":"Free International Shipping","source_url":"https://www.ebay.com/itm/353708296822?hash=item525aa84a76:g:J2UAAOSwEgVhXHKz"},{"title":"Women Boho Floral Jumpsuit Baggy Dungaree Ladies Summer Romper Playsuit Overalls","price":"RMB 167.04 to RMB 253.07","url":"https://i.ebayimg.com/thumbs/images/g/acwAAOSwrI5hFOaD/s-l800.webp","shipping":"Free International Shipping","source_url":"https://www.ebay.com/itm/255075464224?hash=item3b63aeb420:g:acwAAOSwrI5hFOaD"},{"title":"Nano Face Moisturizing Mist Spray Machine USB Facial Mister Humidifier Steamer","price":"RMB 25.33","url":"https://i.ebayimg.com/thumbs/images/g/MtIAAOSwiGViRse7/s-l800.webp","shipping":"+RMB 13.30 shipping","source_url":"https://www.ebay.com/itm/353985666260?hash=item526b309cd4:g:MtIAAOSwiGViRse7"},{"title":"32\" 33\" Car Spare Wheel Tire Covers Hummer H3 Silver Heavy Duty Vinyl PU Leather","price":"RMB 240.50","url":"https://i.ebayimg.com/thumbs/images/g/xKsAAOSwaAphYZoq/s-l800.webp","shipping":"Free International Shipping","source_url":"https://www.ebay.com/itm/353715433557?hash=item525b153055:g:xKsAAOSwaAphYZoq"},{"title":"Rhinestone Ponytail Hair Claws Elegant Luxury Accessories Tassel Banana Clip","price":"RMB 19.79","url":"https://i.ebayimg.com/thumbs/images/g/-lsAAOSwwBViJzM7/s-l800.webp","shipping":"Free International Shipping","source_url":"https://www.ebay.com/itm/224875108316?hash=item345b99d7dc:g:-lsAAOSwwBViJzM7"},{"title":"100Pcs Hydroponic Colonization Pots Vertical Tower Growing System Soilless Farm","price":"RMB 167.04 to RMB 379.60","url":"https://i.ebayimg.com/thumbs/images/g/TL4AAOSwUQNhbCtE/s-l800.webp","shipping":"Free International Shipping","source_url":"https://www.ebay.com/itm/393634001617?hash=item5ba66a32d1:g:TL4AAOSwUQNhbCtE"},{"title":"10pcs Tinned Copper Wire Lugs 8 Gauge 5/16 inch Battery Cable Ends Ring Terminal","price":"RMB 57.15","url":"https://i.ebayimg.com/thumbs/images/g/Ki0AAOSwx41iCy~4/s-l800.webp","shipping":"Free International Shipping","source_url":"https://www.ebay.com/itm/304358544874?hash=item46dd2ed5ea:g:Ki0AAOSwx41iCy~4"},{"title":"Professional Pet Dog Cat Comb Brush Dematting Undercoat Grooming Comb Rake Tool","price":"RMB 34.79 to RMB 38.90","url":"https://i.ebayimg.com/thumbs/images/g/W1cAAOSwevBii18m/s-l800.webp","shipping":"+RMB 6.71 shipping","source_url":"https://www.ebay.com/itm/384905509188?hash=item599e27f944:g:W1cAAOSwevBii18m"},{"title":"Front Bumper Grille Cover Right Side Chrome Trim Fit For BMW X5 E70 2011-2013","price":"RMB 140.24","url":"https://i.ebayimg.com/thumbs/images/g/DycAAOSws7dicDhH/s-l800.webp","shipping":"Free International Shipping","source_url":"https://www.ebay.com/itm/304471236720?hash=item46e3e66070:g:DycAAOSws7dicDhH"},{"title":"45 pcs/pack CUTE KAWII Dog/Cat Animal Decoration DIY Scrapbooking Stickers","price":"RMB 16.66","url":"https://i.ebayimg.com/thumbs/images/g/3p8AAOSwi0hio0XO/s-l800.webp","shipping":"Free International Shipping","source_url":"https://www.ebay.com/itm/374118071263?hash=item571b2cbbdf:g:3p8AAOSwi0hio0XO"},{"title":"AUTH Reformation HARA TOP Ｗhite","price":"RMB 568.10","url":"https://i.ebayimg.com/thumbs/images/g/BzgAAOSwxWphBoG4/s-l800.webp","shipping":"+RMB 66.84 shipping","source_url":"https://www.ebay.com/itm/255073817107?hash=item3b63959213:g:BzgAAOSwxWphBoG4"},{"title":"4 Pcs Guitar Transducer Piezo Under Saddle Pickup Piezo for Guitar Parts","price":"RMB 66.78","url":"https://i.ebayimg.com/thumbs/images/g/XbkAAOSwQItT4gzR/s-l800.webp","shipping":"Free International Shipping","source_url":"https://www.ebay.com/itm/192300653112?hash=item2cc6031a38:g:XbkAAOSwQItT4gzR"},{"title":"For Yamaha YZF600R Thundercat 1996-2007 Frame Slider Crash Falling Protector","price":"RMB 173.72","url":"https://i.ebayimg.com/thumbs/images/g/3v0AAOSwyfNiUpUP/s-l800.webp","shipping":"Free International Shipping","source_url":"https://www.ebay.com/itm/313951037938?hash=item4918f0a9f2:g:3v0AAOSwyfNiUpUP"},{"title":"men's casual bag travel purse waterproof belt zipper tactical","price":"RMB 40.04","url":"https://i.ebayimg.com/thumbs/images/g/34QAAOSwrdpiYEx3/s-l800.webp","shipping":"Free International Shipping","source_url":"https://www.ebay.com/itm/314025587070?hash=item491d62317e:g:34QAAOSwrdpiYEx3"},{"title":"Carbon Fiber Center Console Gear Shift Indicator Trim For Dodge Ram 1500 2018-22","price":"RMB 107.22","url":"https://i.ebayimg.com/thumbs/images/g/zlMAAOSw~XBiOcqz/s-l800.webp","shipping":"+RMB 46.12 shipping","source_url":"https://www.ebay.com/itm/313924605104?hash=item49175d54b0:g:zlMAAOSw~XBiOcqz"},{"title":"Handmade 3d Eyelashes Natural Long Eyelashes Reusable Eyelashes Soft Makeup H0H6","price":"RMB 18.58","url":"https://i.ebayimg.com/thumbs/images/g/mA0AAOSw28ZiA6KT/s-l800.webp","shipping":"+RMB 21.19 shipping","source_url":"https://www.ebay.com/itm/384771870736?hash=item599630d010:g:mA0AAOSw28ZiA6KT"},{"title":"NEW LISTING3.8\" Natural Obsidian Wizard Carved Quartz Crystal skull Reiki Heal Gift 1pc","price":"RMB 209.57","url":"https://i.ebayimg.com/thumbs/images/g/6tkAAOSwSddioxlU/s-l800.webp","shipping":"Free International Shipping","source_url":"https://www.ebay.com/itm/394109762608?hash=item5bc2c5bc30:g:6tkAAOSwSddioxlU"},{"title":"Men's Punk Boys Embroidery Black Straight Summer Denim Jeans Shorts Stretch New","price":"RMB 312.76","url":"https://i.ebayimg.com/thumbs/images/g/wSoAAOSwFTxiVGIj/s-l800.webp","shipping":"Free International Shipping","source_url":"https://www.ebay.com/itm/265639351086?hash=item3dd956d32e:g:wSoAAOSwFTxiVGIj"},{"title":"World Tour 1988 Sexual Chocolate Mr Vintage Men T-Shirt","price":"RMB 106.88 to RMB 120.25","url":"https://i.ebayimg.com/thumbs/images/g/RBQAAOSwMQVhuuRW/s-l800.webp","shipping":"Free International Shipping","source_url":"https://www.ebay.com/itm/403358298040?hash=item5dea072fb8:g:RBQAAOSwMQVhuuRW"},{"title":"Handmade Vintage 925 Silver Turquoise Drop Dangle Earrings Hook Women Jewelry","price":"RMB 9.79","url":"https://i.ebayimg.com/thumbs/images/g/7kIAAOSwG~linKo8/s-l800.webp","shipping":"Free International Shipping","source_url":"https://www.ebay.com/itm/384932343447?hash=item599fc16e97:g:7kIAAOSwG~linKo8"},{"title":"Plus Size Bra Unlined Minimizer Women Underwear Underwire Sexy Big Size 32-52B-F","price":"RMB 85.42","url":"https://i.ebayimg.com/thumbs/images/g/v-QAAOSwxYthZDPS/s-l800.webp","shipping":"Free International Shipping","source_url":"https://www.ebay.com/itm/185100910993?hash=item2b18dfc191:g:v-QAAOSwxYthZDPS"},{"title":"For (2016-2021) Macbook Pro 13\" 14\" 15\" 16\" inch Laptop Hard Case Keyboard Cover","price":"RMB 173.72 to RMB 207.15","url":"https://i.ebayimg.com/thumbs/images/g/gS4AAOSwD6VduTTB/s-l800.webp","shipping":"+RMB 33.35 shipping","source_url":"https://www.ebay.com/itm/334343015506?hash=item4dd8658c52:g:gS4AAOSwD6VduTTB"},{"title":"I Have A Good Heart Women T Shirt Short Sleeve Sarcasm Tshirt Funny Be Kind Tops","price":"RMB 66.04","url":"https://i.ebayimg.com/thumbs/images/g/Yj4AAOSwEX9ioWsk/s-l800.webp","shipping":"Free International Shipping","source_url":"https://www.ebay.com/itm/334468572079?hash=item4ddfe163af:g:Yj4AAOSwEX9ioWsk"},{"title":"Small Edison Screw Socket SES E14 Batten Light Bulb Holder Lamp Surface Fixing","price":"RMB 14.42","url":"https://i.ebayimg.com/thumbs/images/g/Qf0AAOSw9CVbQNfI/s-l800.webp","shipping":"Free International Shipping","source_url":"https://www.ebay.com/itm/283044943060?hash=item41e6cb14d4:g:Qf0AAOSw9CVbQNfI"},{"title":"Case For Samsung Note S 10 5g 10e 9 8 S20 plus Ultra Luxury Leather Phone Back w","price":"RMB 95.17","url":"https://i.ebayimg.com/thumbs/images/g/sAgAAOSwcJRgDcUF/s-l800.webp","shipping":"Free International Shipping","source_url":"https://www.ebay.com/itm/303859099704?hash=item46bf69e838:g:sAgAAOSwcJRgDcUF"},{"title":"Luxury Silver Hoop Earrings Women Anniversary Jewelry Cubic Zirconia A Pair New","price":"RMB 25.06","url":"https://i.ebayimg.com/thumbs/images/g/jQkAAOSwsOVgpihr/s-l800.webp","shipping":"+RMB 33.45 shipping","source_url":"https://www.ebay.com/itm/284679265447?hash=item424834dca7:g:jQkAAOSwsOVgpihr"},{"title":"NEW LISTINGTriPollar Stop Eye 2+ WRINKLE REDUCTION AND SKIN REJUVENATION","price":"RMB 1,664.38","url":"https://i.ebayimg.com/thumbs/images/g/q4AAAOSw~vlioven/s-l800.webp","shipping":"+RMB 200.53 shipping","source_url":"https://www.ebay.com/itm/403709321172?epid=6051040495&hash=item5dfef35fd4:g:q4AAAOSw~vlioven"},{"title":"Gorgeous 925 Silver,Rose Gold Stud Earrings Cubic Zirconia Women Jewelry A Pair","price":"RMB 30.18","url":"https://i.ebayimg.com/thumbs/images/g/SbEAAOSwEhJg~ijB/s-l800.webp","shipping":"Free International Shipping","source_url":"https://www.ebay.com/itm/384295187757?hash=item5979c7352d:g:SbEAAOSwEhJg~ijB"},{"title":"Handlebar Grips Bar End Slider Cap For BMW S1000RR 2010-2020 S1000R/HP4/F800R","price":"RMB 80.55","url":"https://i.ebayimg.com/thumbs/images/g/BF0AAOSwCl9faabi/s-l800.webp","shipping":"+RMB 19.99 shipping","source_url":"https://www.ebay.com/itm/115131616664?hash=item1ace610d98:g:BF0AAOSwCl9faabi"},{"title":"Black Repair Limited-key Front Housing Case Compatible with TK3180 TK2180 Radio","price":"RMB 85.56","url":"https://i.ebayimg.com/thumbs/images/g/ePUAAOSwLi9hbeeU/s-l800.webp","shipping":"+RMB 23.39 shipping","source_url":"https://www.ebay.com/itm/313716595759?hash=item490af75c2f:g:ePUAAOSwLi9hbeeU"},{"title":"5pcs natural mahogany obsidian hand carved crystal mushroom reiki healing gems","price":"RMB 22.26","url":"https://i.ebayimg.com/thumbs/images/g/1lkAAOSwJL1imgbz/s-l800.webp","shipping":"Free International Shipping","source_url":"https://www.ebay.com/itm/314022399738?hash=item491d318efa:g:1lkAAOSwJL1imgbz"},{"title":"OEM Genuine Ford F150 F250 2015-2021 4’ to 8' SYNC3 conversion upgrade w/Carplay","price":"RMB 8,555.86","url":"https://i.ebayimg.com/thumbs/images/g/2SEAAOSwsUJfv9WM/s-l800.webp","shipping":"Free International Shipping","source_url":"https://www.ebay.com/itm/325215012429?hash=item4bb853464d:g:2SEAAOSwsUJfv9WM"},{"title":"1PCS ICOP-6054 PC104 90days warranty via DHL or FedEx","price":"RMB 895.63","url":"https://i.ebayimg.com/thumbs/images/g/zbYAAOSwXC1fkbMX/s-l800.webp","shipping":"+RMB 200.53 shipping","source_url":"https://www.ebay.com/itm/224204793337?hash=item3433a5a5f9:g:zbYAAOSwXC1fkbMX"},{"title":"10Pcs Minnow Fishing Lures Bass Crankbait Hooks Tackle Crank Baits Fishing Set","price":"RMB 50.60","url":"https://i.ebayimg.com/thumbs/images/g/2voAAOSwGvldX1LL/s-l800.webp","shipping":"Free International Shipping","source_url":"https://www.ebay.com/itm/194732019354?hash=item2d56eece9a:g:2voAAOSwGvldX1LL"},{"title":"Women Headband Retro Wired Head Scarf Rockabilly Hair Band Head Wrap New Vintage","price":"RMB 12.63 to RMB 19.99","url":"https://i.ebayimg.com/thumbs/images/g/1iYAAOSwtxxbYqhX/s-l800.webp","shipping":"Free International Shipping","source_url":"https://www.ebay.com/itm/381846762173?hash=item58e7d732bd:g:1iYAAOSwtxxbYqhX"},{"title":"29mm Black Watch Dial w/Green Luminous Replacement for NH35 Watch Movement Parts","price":"RMB 66.89","url":"https://i.ebayimg.com/thumbs/images/g/yBUAAOSwdXVgkPEL/s-l800.webp","shipping":"+RMB 8.22 shipping","source_url":"https://www.ebay.com/itm/313516979890?hash=item48ff1176b2:g:yBUAAOSwdXVgkPEL"},{"title":"Women Retro Wired Bendy Headband Solid Rabbit Ears Headband Hair Head Band Wrap","price":"RMB 11.96 to RMB 14.64","url":"https://i.ebayimg.com/thumbs/images/g/MlEAAOSwMvViZnle/s-l800.webp","shipping":"Free International Shipping","source_url":"https://www.ebay.com/itm/394045352267?hash=item5bbeeee94b:g:MlEAAOSwMvViZnle"},{"title":"Original X-Level Matte Cover For iPhone 13 Pro Max 12 Ultra Thin Soft Back Case","price":"RMB 53.34","url":"https://i.ebayimg.com/thumbs/images/g/Eg4AAOSwF4lfiFAb/s-l800.webp","shipping":"+RMB 19.99 shipping","source_url":"https://www.ebay.com/itm/224195299997?hash=item343314ca9d:g:Eg4AAOSwF4lfiFAb"},{"title":"Green Men Suits Pinstripe 2 Pieces Wool Work Wear Formal Wedding Groom Tailored","price":"RMB 418.44 to RMB 695.90","url":"https://i.ebayimg.com/thumbs/images/g/5OsAAOSwjY1iixXa/s-l800.webp","shipping":"+RMB 200.46 shipping","source_url":"https://www.ebay.com/itm/165499135944?hash=item26888467c8:g:5OsAAOSwjY1iixXa"},{"title":"10Pcs Craft Natural Peacock Feathers Wedding Party Bouquet Decoration 10-12\"","price":"RMB 26.67","url":"https://i.ebayimg.com/thumbs/images/g/phwAAOSwCCpceKt7/s-l800.webp","shipping":"+RMB 9.96 shipping","source_url":"https://www.ebay.com/itm/402333460815?hash=item5dacf1694f:g:phwAAOSwCCpceKt7"},{"title":"Carbon Fiber Car Rear Bumper Trunk Protector Corner Trim Sticker Car Accessories","price":"RMB 81.75","url":"https://i.ebayimg.com/thumbs/images/g/TdMAAOSwGxtiBJ86/s-l800.webp","shipping":"Free International Shipping","source_url":"https://www.ebay.com/itm/384726012097?hash=item59937510c1:g:TdMAAOSwGxtiBJ86"},{"title":"Silver Holographic Car SUV Hood Side Body Vinyl Graphics Decal Graphics Sticker","price":"RMB 69.78 to RMB 158.68","url":"https://i.ebayimg.com/thumbs/images/g/PBEAAOSwMJdiPD3S/s-l800.webp","shipping":"Free International Shipping","source_url":"https://www.ebay.com/itm/224902543428?hash=item345d3c7844:g:PBEAAOSwMJdiPD3S"},{"title":"Eggdog Plush Doll Twisting Eggdog Funny Plush Soft Toy Kids Birthday Gift","price":"RMB 75.93","url":"https://i.ebayimg.com/thumbs/images/g/H9MAAOSwjLFiLGJG/s-l800.webp","shipping":"+RMB 66.78 shipping","source_url":"https://www.ebay.com/itm/374042305478?hash=item5716a8a3c6:g:H9MAAOSwjLFiLGJG"},{"title":"USB Programming Cable for Alinco DJ-191 DJ-193 ERW-7 ERW-4C","price":"RMB 66.78","url":"https://i.ebayimg.com/thumbs/images/g/SAYAAOSwF2pg-NIe/s-l800.webp","shipping":"+RMB 33.42 shipping","source_url":"https://www.ebay.com/itm/324420708731?hash=item4b88fb297b:g:SAYAAOSwF2pg-NIe"},{"title":"UNIVERSAL MUGEN CARBON ALUMINUM CAR BATTERY TIE DOWN MOUNT BRACKET BRACE BAR","price":"RMB 93.58","url":"https://i.ebayimg.com/thumbs/images/g/DeMAAOSwxZthChkB/s-l800.webp","shipping":"+RMB 20.05 shipping","source_url":"https://www.ebay.com/itm/255148760371?hash=item3b680d1d33:g:DeMAAOSwxZthChkB"},{"title":"2 Diptera mosquito fly Burmite Myanmar Burmese Amber insect fossil dinosaur age","price":"RMB 3.68","url":"https://i.ebayimg.com/thumbs/images/g/YlwAAOSweLdimgbt/s-l800.webp","shipping":"Free International Shipping","source_url":"https://www.ebay.com/itm/265720856259?hash=item3dde327ec3:g:YlwAAOSweLdimgbt"},{"title":"12 Colors Nylon 3# Invisible Zippers 60cm For Tailor Sewing Craft Coil Zipper","price":"RMB 5.77 to RMB 28.47","url":"https://i.ebayimg.com/thumbs/images/g/cn0AAOSwTFNidl6-/s-l800.webp","shipping":"Free International Shipping","source_url":"https://www.ebay.com/itm/394064008732?hash=item5bc00b961c:g:cn0AAOSwTFNidl6-"},{"title":"Front + Rear skid plates for Tesla Model Y 2020 2021 2022 2pcs black","price":"RMB 2,606.80","url":"https://i.ebayimg.com/thumbs/images/g/CqsAAOSwm4Vienmo/s-l800.webp","shipping":"Free International Shipping","source_url":"https://www.ebay.com/itm/234546521802?hash=item369c0fe6ca:g:CqsAAOSwm4Vienmo"},{"title":"1* - Soldering Station Iron Heating ELEMENT 132A 40W For-YIHUA 898D 898BD 862D","price":"RMB 49.20","url":"https://i.ebayimg.com/thumbs/images/g/prgAAOSwQSVilC7r/s-l800.webp","shipping":"Free International Shipping","source_url":"https://www.ebay.com/itm/185445715022?hash=item2b2d6d0c4e:g:prgAAOSwQSVilC7r"},{"title":"New Turbo RHE61 Turbocharger 114400-3320 for HITACHI EX200-5 W/ Isuzu 6BG1T Engi","price":"RMB 1,845.86","url":"https://i.ebayimg.com/thumbs/images/g/irIAAOSwHhRb68Rs/s-l800.webp","shipping":"Free International Shipping","source_url":"https://www.ebay.com/itm/273856617566?epid=7025869812&hash=item3fc3205c5e:g:irIAAOSwHhRb68Rs"},{"title":"Stylish New Women One Sleeve Bandage Patchwork Solid Skinny Casual Top Party","price":"RMB 111.83","url":"https://i.ebayimg.com/thumbs/images/g/VzMAAOSw2lZhJg32/s-l800.webp","shipping":"Free International Shipping","source_url":"https://www.ebay.com/itm/353642192492?hash=item5256b79e6c:g:VzMAAOSw2lZhJg32"},{"title":"Luxury Fashion Men Wrist Watch Leather Band Quartz Business Simple Blue Glass","price":"RMB 26.67","url":"https://i.ebayimg.com/thumbs/images/g/dK4AAOSw7jJig3ND/s-l800.webp","shipping":"Free International Shipping","source_url":"https://www.ebay.com/itm/374114714380?hash=item571af9830c:g:dK4AAOSw7jJig3ND"},{"title":"6pcs For Benz ML M Class ML350 ML450 2006-2011 W164 Pillar Post Door Trim Cover","price":"RMB 140.30","url":"https://i.ebayimg.com/thumbs/images/g/P~IAAOSwFfphyYdP/s-l800.webp","shipping":"Free International Shipping","source_url":"https://www.ebay.com/itm/194671643466?hash=item2d53558b4a:g:P~IAAOSwFfphyYdP"},{"title":"Tibetan Silver Necklace W/*12Aminals* 福 Prayer Wheel Hollowing Pendant","price":"RMB 100.20","url":"https://i.ebayimg.com/thumbs/images/g/uvwAAOSwjdliVlOK/s-l800.webp","shipping":"Free International Shipping","source_url":"https://www.ebay.com/itm/314022398255?hash=item491d31892f:g:uvwAAOSwjdliVlOK"},{"title":"66g Natural Polished Pork Stone Meat Rough Specimen","price":"RMB 43.45","url":"https://i.ebayimg.com/thumbs/images/g/wXUAAOSwoMVimgSu/s-l800.webp","shipping":"Free International Shipping","source_url":"https://www.ebay.com/itm/314022397963?hash=item491d31880b:g:wXUAAOSwoMVimgSu"},{"title":"Samsung Galaxy S8 G950U 64GB Unlocked Smartphone AT&T T-Mobile SHADED VERY GOOD","price":"RMB 660.34","url":"https://i.ebayimg.com/thumbs/images/g/6QwAAOSw45FiTIYU/s-l800.webp","shipping":"Free International Shipping","source_url":"https://www.ebay.com/itm/225009658138?epid=19024622382&hash=item34639ee91a:g:6QwAAOSw45FiTIYU"},{"title":"Left Driver Inner LED Tail Light Rear brake Lamp Assy p For AUDI A6 C7 2012-2016","price":"RMB 621.64","url":"https://i.ebayimg.com/thumbs/images/g/rcUAAOSwaB1f~n~p/s-l800.webp","shipping":"+RMB 96.92 shipping","source_url":"https://www.ebay.com/itm/393069257399?hash=item5b84c0e2b7:g:rcUAAOSwaB1f~n~p"},{"title":"3K Carbon Bicycle Seatpost MTB 31.6 Adjustable Road Bike Seat Tube 27.2*350/400","price":"RMB 173.06","url":"https://i.ebayimg.com/thumbs/images/g/Ro8AAOSwHOVgmQR5/s-l800.webp","shipping":"+RMB 33.35 shipping","source_url":"https://www.ebay.com/itm/264996090769?hash=item3db2ff7391:g:Ro8AAOSwHOVgmQR5"},{"title":"Rare 47.9G Natural Agate Geode Quartz Crystal Mineral Specimen Healing W060306","price":"RMB 46.79","url":"https://i.ebayimg.com/thumbs/images/g/~W4AAOSwVYpimgaf/s-l800.webp","shipping":"Free International Shipping","source_url":"https://www.ebay.com/itm/125349601001?hash=item1d2f6b1ee9:g:~W4AAOSwVYpimgaf"},{"title":"Vintage Men Cufflinks Jewelry Rhinestone Classic Silver Cuff Links Tie Clasps","price":"RMB 96.52","url":"https://i.ebayimg.com/thumbs/images/g/290AAOSwMg5idjIC/s-l800.webp","shipping":"Free International Shipping","source_url":"https://www.ebay.com/itm/354047656978?hash=item526ee28412:g:290AAOSwMg5idjIC"},{"title":"Barefoot Sandals 1pcs Boho Gypsy Beach Black Chain Anklet Constellation","price":"RMB 10.90","url":"https://i.ebayimg.com/thumbs/images/g/PCEAAOSwjk9ZP1IB/s-l800.webp","shipping":"+RMB 3.27 shipping","source_url":"https://www.ebay.com/itm/391814179996?hash=item5b39f1ec9c:g:PCEAAOSwjk9ZP1IB"},{"title":"Women Girls White Pearl Hairpin Snap Barrette Hairpin Bobby Hair Accessories","price":"RMB 5.24","url":"https://i.ebayimg.com/thumbs/images/g/q90AAOSwgIpgtL7w/s-l800.webp","shipping":"Free International Shipping","source_url":"https://www.ebay.com/itm/194469358072?hash=item2d4746e9f8:g:q90AAOSwgIpgtL7w"}]